{"v":"5.9.4","fr":29.9700012207031,"ip":0,"op":90.0000036657751,"w":240,"h":240,"nm":"å¤´åå¨ç»_lottie","ddd":0,"assets":[],"layers":[{"ddd":0,"ind":1,"ty":3,"nm":"ä½ç§»_c","sr":1,"ks":{"o":{"a":0,"k":0,"ix":11},"r":{"a":0,"k":0,"ix":10},"p":{"a":0,"k":[103.231,259.731,0],"ix":2,"l":2},"a":{"a":0,"k":[50,50,0],"ix":1,"l":2},"s":{"a":0,"k":[100,100,100],"ix":6,"l":2}},"ao":0,"ip":0,"op":150.000006109625,"st":0,"bm":0},{"ddd":0,"ind":2,"ty":3,"nm":"face_c","parent":13,"sr":1,"ks":{"o":{"a":0,"k":0,"ix":11},"r":{"a":0,"k":0,"ix":10},"p":{"a":1,"k":[{"i":{"x":0.833,"y":0.833},"o":{"x":0.167,"y":0.167},"t":11,"s":[72.166,57.023,0],"e":[72.166,30.589,0],"to":[0,-4.406,0],"ti":[0,1.611,0]},{"i":{"x":0.833,"y":0.833},"o":{"x":0.167,"y":0.167},"t":21,"s":[72.166,30.589,0],"e":[72.166,47.356,0],"to":[0,-1.611,0],"ti":[0,-2.794,0]},{"t":27.0000010997325}],"ix":2,"l":2,"x":"var $bm_rt;\nvar amp, freq, decay, n, n, t, t, v;\ntry {\n    amp = $bm_div(effect('Elastic: ä½ç½® 2')(1), 200);\n    freq = $bm_div(effect('Elastic: ä½ç½® 2')(2), 30);\n    decay = $bm_div(effect('Elastic: ä½ç½® 2')(3), 10);\n    $bm_rt = n = 0;\n    if (numKeys > 0) {\n        $bm_rt = n = nearestKey(time).index;\n        if (key(n).time > time) {\n            n--;\n        }\n    }\n    if (n == 0) {\n        $bm_rt = t = 0;\n    } else {\n        $bm_rt = t = $bm_sub(time, key(n).time);\n    }\n    if (n > 0) {\n        v = velocityAtTime($bm_sub(key(n).time, $bm_div(thisComp.frameDuration, 10)));\n        $bm_rt = $bm_sum(value, $bm_div($bm_mul($bm_mul(v, amp), Math.sin($bm_mul($bm_mul($bm_mul(freq, t), 2), Math.PI))), Math.exp($bm_mul(decay, t))));\n    } else {\n        $bm_rt = value;\n    }\n} catch (e$$4) {\n    $bm_rt = value = value;\n}"},"a":{"a":0,"k":[0,0,0],"ix":1,"l":2},"s":{"a":0,"k":[51,51,100],"ix":6,"l":2}},"ao":0,"ef":[{"ty":5,"nm":"Elastic: ä½ç½®","np":5,"mn":"Pseudo/MDS Elastic Controller","ix":1,"en":1,"ef":[{"ty":0,"nm":"Amplitude","mn":"Pseudo/MDS Elastic Controller-0001","ix":1,"v":{"a":0,"k":20,"ix":1}},{"ty":0,"nm":"Frequency","mn":"Pseudo/MDS Elastic Controller-0002","ix":2,"v":{"a":0,"k":40,"ix":2}},{"ty":0,"nm":"Decay","mn":"Pseudo/MDS Elastic Controller-0003","ix":3,"v":{"a":0,"k":60,"ix":3}}]},{"ty":5,"nm":"Elastic: ä½ç½® 2","np":5,"mn":"Pseudo/MDS Elastic Controller","ix":2,"en":1,"ef":[{"ty":0,"nm":"Amplitude","mn":"Pseudo/MDS Elastic Controller-0001","ix":1,"v":{"a":0,"k":20,"ix":1}},{"ty":0,"nm":"Frequency","mn":"Pseudo/MDS Elastic Controller-0002","ix":2,"v":{"a":0,"k":40,"ix":2}},{"ty":0,"nm":"Decay","mn":"Pseudo/MDS Elastic Controller-0003","ix":3,"v":{"a":0,"k":60,"ix":3}}]}],"ip":0,"op":150.000006109625,"st":0,"bm":0},{"ddd":0,"ind":3,"ty":3,"nm":"body_c","parent":1,"sr":1,"ks":{"o":{"a":0,"k":0,"ix":11},"r":{"a":0,"k":0,"ix":10},"p":{"a":1,"k":[{"i":{"x":0.833,"y":0.833},"o":{"x":0.167,"y":0.167},"t":2,"s":[73.769,191.269,0],"e":[73.769,11.269,0],"to":[0,-30,0],"ti":[0,30,0]},{"t":17.0000006924242}],"ix":2,"l":2,"x":"var $bm_rt;\nvar amp, freq, decay, n, n, t, t, v;\ntry {\n    amp = $bm_div(effect('Elastic: ä½ç½® 2')(1), 200);\n    freq = $bm_div(effect('Elastic: ä½ç½® 2')(2), 30);\n    decay = $bm_div(effect('Elastic: ä½ç½® 2')(3), 10);\n    $bm_rt = n = 0;\n    if (numKeys > 0) {\n        $bm_rt = n = nearestKey(time).index;\n        if (key(n).time > time) {\n            n--;\n        }\n    }\n    if (n == 0) {\n        $bm_rt = t = 0;\n    } else {\n        $bm_rt = t = $bm_sub(time, key(n).time);\n    }\n    if (n > 0) {\n        v = velocityAtTime($bm_sub(key(n).time, $bm_div(thisComp.frameDuration, 10)));\n        $bm_rt = $bm_sum(value, $bm_div($bm_mul($bm_mul(v, amp), Math.sin($bm_mul($bm_mul($bm_mul(freq, t), 2), Math.PI))), Math.exp($bm_mul(decay, t))));\n    } else {\n        $bm_rt = value;\n    }\n} catch (e$$4) {\n    $bm_rt = value = value;\n}"},"a":{"a":0,"k":[0,0,0],"ix":1,"l":2},"s":{"a":0,"k":[100,100,100],"ix":6,"l":2}},"ao":0,"ef":[{"ty":5,"nm":"Elastic: ä½ç½®","np":5,"mn":"Pseudo/MDS Elastic Controller","ix":1,"en":1,"ef":[{"ty":0,"nm":"Amplitude","mn":"Pseudo/MDS Elastic Controller-0001","ix":1,"v":{"a":0,"k":20,"ix":1}},{"ty":0,"nm":"Frequency","mn":"Pseudo/MDS Elastic Controller-0002","ix":2,"v":{"a":0,"k":40,"ix":2}},{"ty":0,"nm":"Decay","mn":"Pseudo/MDS Elastic Controller-0003","ix":3,"v":{"a":0,"k":60,"ix":3}}]},{"ty":5,"nm":"Elastic: ä½ç½® 2","np":5,"mn":"Pseudo/MDS Elastic Controller","ix":2,"en":1,"ef":[{"ty":0,"nm":"Amplitude","mn":"Pseudo/MDS Elastic Controller-0001","ix":1,"v":{"a":0,"k":20,"ix":1}},{"ty":0,"nm":"Frequency","mn":"Pseudo/MDS Elastic Controller-0002","ix":2,"v":{"a":0,"k":40,"ix":2}},{"ty":0,"nm":"Decay","mn":"Pseudo/MDS Elastic Controller-0003","ix":3,"v":{"a":0,"k":60,"ix":3}}]}],"ip":0,"op":150.000006109625,"st":0,"bm":0},{"ddd":0,"ind":4,"ty":4,"nm":"å·¦ç¼ 2","parent":2,"sr":1,"ks":{"o":{"a":0,"k":100,"ix":11},"r":{"a":0,"k":0,"ix":10},"p":{"a":0,"k":[-42.158,-0.301,0],"ix":2,"l":2},"a":{"a":0,"k":[7.67,8.353,0],"ix":1,"l":2},"s":{"a":0,"k":[196.078,196.078,100],"ix":6,"l":2}},"ao":0,"ef":[{"ty":28,"nm":"è®¾ç½®é®ç½©","np":8,"mn":"ADBE Set Matte3","ix":1,"en":1,"ef":[{"ty":10,"nm":"ä»å¾å±è·åé®ç½©","mn":"ADBE Set Matte3-0001","ix":1,"v":{"a":0,"k":4,"ix":1}},{"ty":7,"nm":"ç¨äºé®ç½©","mn":"ADBE Set Matte3-0002","ix":2,"v":{"a":0,"k":4,"ix":2}},{"ty":7,"nm":"åè½¬é®ç½©","mn":"ADBE Set Matte3-0003","ix":3,"v":{"a":0,"k":0,"ix":3}},{"ty":7,"nm":"å¦æå¾å±å¤§å°ä¸å","mn":"ADBE Set Matte3-0004","ix":4,"v":{"a":0,"k":1,"ix":4}},{"ty":7,"nm":"å°é®ç½©ä¸åå§å¾ååæ","mn":"ADBE Set Matte3-0005","ix":5,"v":{"a":0,"k":1,"ix":5}},{"ty":7,"nm":"é¢ä¹é®ç½©å¾å±","mn":"ADBE Set Matte3-0006","ix":6,"v":{"a":0,"k":1,"ix":6}}]}],"shapes":[{"ty":"gr","it":[{"ind":0,"ty":"sh","ix":1,"ks":{"a":0,"k":{"i":[[-0.313,-4.318],[3.926,-0.285],[0.313,4.318],[-3.925,0.285]],"o":[[0.313,4.317],[-3.925,0.284],[-0.313,-4.318],[3.925,-0.285]],"v":[[7.108,-0.515],[0.566,7.819],[-7.108,0.516],[-0.568,-7.818]],"c":true},"ix":2},"nm":"è·¯å¾ 1","mn":"ADBE Vector Shape - Group","hd":false},{"ty":"fl","c":{"a":0,"k":[0.136999990426,0.097999999102,0.086000001197,1],"ix":4},"o":{"a":0,"k":100,"ix":5},"r":1,"bm":0,"nm":"å¡«å 1","mn":"ADBE Vector Graphic - Fill","hd":false},{"ty":"tr","p":{"a":0,"k":[7.67,8.353],"ix":2},"a":{"a":0,"k":[0,0],"ix":1},"s":{"a":0,"k":[100,100],"ix":3},"r":{"a":0,"k":0,"ix":6},"o":{"a":0,"k":100,"ix":7},"sk":{"a":0,"k":0,"ix":4},"sa":{"a":0,"k":0,"ix":5},"nm":"åæ¢"}],"nm":"ç» 1","np":2,"cix":2,"bm":0,"ix":1,"mn":"ADBE Vector Group","hd":false}],"ip":53.0000021587343,"op":150.000006109625,"st":52.0000021180034,"ct":1,"bm":0},{"ddd":0,"ind":5,"ty":4,"nm":"ææ/å¤´åå¨ç».ai","cl":"ai","parent":1,"sr":1,"ks":{"o":{"a":1,"k":[{"i":{"x":[0.833],"y":[0.833]},"o":{"x":[0.167],"y":[0.167]},"t":46,"s":[0],"e":[100]},{"i":{"x":[0.833],"y":[0.833]},"o":{"x":[0.167],"y":[0.167]},"t":49,"s":[100],"e":[100]},{"i":{"x":[0.833],"y":[0.833]},"o":{"x":[0.167],"y":[0.167]},"t":54,"s":[100],"e":[0]},{"t":58.0000023623884}],"ix":11},"r":{"a":0,"k":0,"ix":10},"p":{"a":0,"k":[26.231,-91.269,0],"ix":2,"l":2},"a":{"a":0,"k":[18.962,18.963,0],"ix":1,"l":2},"s":{"a":1,"k":[{"i":{"x":[0.667,0.667,0.667],"y":[1,1,1]},"o":{"x":[0.333,0.333,0.333],"y":[0,0,0]},"t":46,"s":[0,0,100],"e":[100,100,100]},{"t":49.0000019958109}],"ix":6,"l":2}},"ao":0,"shapes":[{"ty":"gr","it":[{"ind":0,"ty":"sh","ix":1,"ks":{"a":0,"k":{"i":[[2.505,0],[0.585,-2.436],[0,0],[0,0],[0,-2.505],[-2.436,-0.585],[0,0],[0,0],[-2.505,0],[-0.585,2.437],[0,0],[0,0],[0,2.505],[2.436,0.586],[0,0],[0,0]],"o":[[-2.505,0],[0,0],[0,0],[-2.436,0.586],[0,2.505],[0,0],[0,0],[0.585,2.437],[2.505,0],[0,0],[0,0],[2.436,-0.585],[0,-2.505],[0,0],[0,0],[-0.585,-2.436]],"v":[[0,-18.713],[-5.249,-14.575],[-7.056,-7.057],[-14.575,-5.249],[-18.712,-0.001],[-14.575,5.249],[-7.056,7.057],[-5.249,14.575],[0,18.713],[5.249,14.575],[7.056,7.057],[14.575,5.249],[18.712,-0.001],[14.575,-5.249],[7.056,-7.057],[5.249,-14.575]],"c":true},"ix":2},"nm":"è·¯å¾ 1","mn":"ADBE Vector Shape - Group","hd":false},{"ind":1,"ty":"sh","ix":2,"ks":{"a":0,"k":{"i":[[-0.169,0],[-0.049,-0.204],[0,0],[-0.145,-0.035],[0,0],[0.407,-0.098],[0,0],[0.035,-0.146],[0,0],[0.169,0],[0.049,0.204],[0,0],[0.146,0.035],[0,0],[-0.407,0.098],[0,0],[-0.035,0.145],[0,0]],"o":[[0.169,0],[0,0],[0.035,0.145],[0,0],[0.407,0.098],[0,0],[-0.145,0.035],[0,0],[-0.049,0.204],[-0.169,0],[0,0],[-0.035,-0.146],[0,0],[-0.407,-0.098],[0,0],[0.146,-0.035],[0,0],[0.049,-0.204]],"v":[[0,-13.713],[0.388,-13.406],[2.853,-3.148],[3.147,-2.854],[13.407,-0.387],[13.407,0.387],[3.147,2.852],[2.853,3.148],[0.388,13.407],[0,13.713],[-0.387,13.407],[-2.853,3.148],[-3.147,2.852],[-13.407,0.387],[-13.407,-0.387],[-3.147,-2.854],[-2.853,-3.148],[-0.387,-13.406]],"c":true},"ix":2},"nm":"è·¯å¾ 2","mn":"ADBE Vector Shape - Group","hd":false},{"ty":"mm","mm":1,"nm":"åå¹¶è·¯å¾ 1","mn":"ADBE Vector Filter - Merge","hd":false},{"ty":"fl","c":{"a":0,"k":[0,0,0,1],"ix":4},"o":{"a":0,"k":100,"ix":5},"r":1,"bm":0,"nm":"å¡«å 1","mn":"ADBE Vector Graphic - Fill","hd":false},{"ty":"tr","p":{"a":0,"k":[18.962,18.963],"ix":2},"a":{"a":0,"k":[0,0],"ix":1},"s":{"a":0,"k":[100,100],"ix":3},"r":{"a":0,"k":0,"ix":6},"o":{"a":0,"k":100,"ix":7},"sk":{"a":0,"k":0,"ix":4},"sa":{"a":0,"k":0,"ix":5},"nm":"åæ¢"}],"nm":"ç» 1","np":4,"cix":2,"bm":0,"ix":1,"mn":"ADBE Vector Group","hd":false},{"ty":"gr","it":[{"ind":0,"ty":"sh","ix":1,"ks":{"a":0,"k":{"i":[[1.344,0],[0.314,1.309],[0,0],[0,0],[0.001,1.345],[-1.307,0.315],[0,0],[0,0],[-1.345,0],[-0.315,-1.306],[0,0],[0,0],[0.001,-1.345],[1.307,-0.314],[0,0],[0,0]],"o":[[-1.346,0],[0,0],[0,0],[-1.306,-0.313],[-0.001,-1.345],[0,0],[0,0],[0.314,-1.307],[1.344,0],[0,0],[0,0],[1.31,0.316],[-0.001,1.345],[0,0],[0,0],[-0.315,1.309]],"v":[[0,16.212],[-2.818,13.99],[-4.983,4.984],[-13.991,2.818],[-16.212,0.001],[-13.993,-2.818],[-4.983,-4.982],[-2.818,-13.991],[0,-16.212],[2.818,-13.993],[4.983,-4.982],[13.991,-2.818],[16.212,0.001],[13.991,2.819],[4.983,4.984],[2.818,13.991]],"c":true},"ix":2},"nm":"è·¯å¾ 1","mn":"ADBE Vector Shape - Group","hd":false},{"ty":"fl","c":{"a":0,"k":[1,1,1,1],"ix":4},"o":{"a":0,"k":100,"ix":5},"r":1,"bm":0,"nm":"å¡«å 1","mn":"ADBE Vector Graphic - Fill","hd":false},{"ty":"tr","p":{"a":0,"k":[18.962,18.962],"ix":2},"a":{"a":0,"k":[0,0],"ix":1},"s":{"a":0,"k":[100,100],"ix":3},"r":{"a":0,"k":0,"ix":6},"o":{"a":0,"k":100,"ix":7},"sk":{"a":0,"k":0,"ix":4},"sa":{"a":0,"k":0,"ix":5},"nm":"åæ¢"}],"nm":"ç» 2","np":2,"cix":2,"bm":0,"ix":2,"mn":"ADBE Vector Group","hd":false}],"ip":46.0000018736184,"op":58.0000023623884,"st":0,"ct":1,"bm":0},{"ddd":0,"ind":6,"ty":4,"nm":"ç¨ç¼","parent":2,"sr":1,"ks":{"o":{"a":0,"k":100,"ix":11},"r":{"a":0,"k":0,"ix":10},"p":{"a":0,"k":[-42.647,2.058,0],"ix":2,"l":2},"a":{"a":0,"k":[-21.75,10.75,0],"ix":1,"l":2},"s":{"a":0,"k":[161.476,161.476,100],"ix":6,"l":2}},"ao":0,"shapes":[{"ty":"gr","it":[{"ind":0,"ty":"sh","ix":1,"ks":{"a":0,"k":{"i":[[0,0],[0,0],[0,0]],"o":[[0,0],[0,0],[0,0]],"v":[[-25.56,3.899],[-12.58,10.295],[-21.345,16.965]],"c":false},"ix":2},"nm":"è·¯å¾ 1","mn":"ADBE Vector Shape - Group","hd":false},{"ty":"st","c":{"a":0,"k":[0.137254908681,0.098039224744,0.086274512112,1],"ix":3},"o":{"a":0,"k":100,"ix":4},"w":{"a":0,"k":6.35,"ix":5},"lc":2,"lj":2,"bm":0,"nm":"æè¾¹ 1","mn":"ADBE Vector Graphic - Stroke","hd":false},{"ty":"tr","p":{"a":0,"k":[0,0],"ix":2},"a":{"a":0,"k":[0,0],"ix":1},"s":{"a":0,"k":[100,100],"ix":3},"r":{"a":0,"k":0,"ix":6},"o":{"a":0,"k":100,"ix":7},"sk":{"a":0,"k":0,"ix":4},"sa":{"a":0,"k":0,"ix":5},"nm":"åæ¢"}],"nm":"å½¢ç¶ 1","np":3,"cix":2,"bm":0,"ix":1,"mn":"ADBE Vector Group","hd":false}],"ip":46.0000018736184,"op":53.0000021587343,"st":0,"ct":1,"bm":0},{"ddd":0,"ind":7,"ty":4,"nm":"å·¦ç¼","parent":2,"sr":1,"ks":{"o":{"a":0,"k":100,"ix":11},"r":{"a":0,"k":0,"ix":10},"p":{"a":0,"k":[-42.158,-0.301,0],"ix":2,"l":2},"a":{"a":0,"k":[7.67,8.353,0],"ix":1,"l":2},"s":{"a":1,"k":[{"i":{"x":[0.833,0.833,0.833],"y":[0.833,0.833,0.833]},"o":{"x":[0.167,0.167,0.167],"y":[0.167,0.167,0.167]},"t":42,"s":[196.078,196.078,100],"e":[196.078,0,100]},{"t":46.0000018736184}],"ix":6,"l":2}},"ao":0,"ef":[{"ty":28,"nm":"è®¾ç½®é®ç½©","np":8,"mn":"ADBE Set Matte3","ix":1,"en":1,"ef":[{"ty":10,"nm":"ä»å¾å±è·åé®ç½©","mn":"ADBE Set Matte3-0001","ix":1,"v":{"a":0,"k":15,"ix":1}},{"ty":7,"nm":"ç¨äºé®ç½©","mn":"ADBE Set Matte3-0002","ix":2,"v":{"a":0,"k":4,"ix":2}},{"ty":7,"nm":"åè½¬é®ç½©","mn":"ADBE Set Matte3-0003","ix":3,"v":{"a":0,"k":0,"ix":3}},{"ty":7,"nm":"å¦æå¾å±å¤§å°ä¸å","mn":"ADBE Set Matte3-0004","ix":4,"v":{"a":0,"k":1,"ix":4}},{"ty":7,"nm":"å°é®ç½©ä¸åå§å¾ååæ","mn":"ADBE Set Matte3-0005","ix":5,"v":{"a":0,"k":1,"ix":5}},{"ty":7,"nm":"é¢ä¹é®ç½©å¾å±","mn":"ADBE Set Matte3-0006","ix":6,"v":{"a":0,"k":1,"ix":6}}]}],"shapes":[{"ty":"gr","it":[{"ind":0,"ty":"sh","ix":1,"ks":{"a":0,"k":{"i":[[-0.313,-4.318],[3.926,-0.285],[0.313,4.318],[-3.925,0.285]],"o":[[0.313,4.317],[-3.925,0.284],[-0.313,-4.318],[3.925,-0.285]],"v":[[7.108,-0.515],[0.566,7.819],[-7.108,0.516],[-0.568,-7.818]],"c":true},"ix":2},"nm":"è·¯å¾ 1","mn":"ADBE Vector Shape - Group","hd":false},{"ty":"fl","c":{"a":0,"k":[0.136999990426,0.097999999102,0.086000001197,1],"ix":4},"o":{"a":0,"k":100,"ix":5},"r":1,"bm":0,"nm":"å¡«å 1","mn":"ADBE Vector Graphic - Fill","hd":false},{"ty":"tr","p":{"a":0,"k":[7.67,8.353],"ix":2},"a":{"a":0,"k":[0,0],"ix":1},"s":{"a":0,"k":[100,100],"ix":3},"r":{"a":0,"k":0,"ix":6},"o":{"a":0,"k":100,"ix":7},"sk":{"a":0,"k":0,"ix":4},"sa":{"a":0,"k":0,"ix":5},"nm":"åæ¢"}],"nm":"ç» 1","np":2,"cix":2,"bm":0,"ix":1,"mn":"ADBE Vector Group","hd":false}],"ip":0,"op":46.0000018736184,"st":0,"ct":1,"bm":0},{"ddd":0,"ind":8,"ty":4,"nm":"å³ç¼","parent":2,"sr":1,"ks":{"o":{"a":0,"k":100,"ix":11},"r":{"a":0,"k":0,"ix":10},"p":{"a":0,"k":[46.104,-6.846,0],"ix":2,"l":2},"a":{"a":0,"k":[7.67,8.353,0],"ix":1,"l":2},"s":{"a":0,"k":[196.078,196.078,100],"ix":6,"l":2}},"ao":0,"ef":[{"ty":28,"nm":"è®¾ç½®é®ç½©","np":8,"mn":"ADBE Set Matte3","ix":1,"en":1,"ef":[{"ty":10,"nm":"ä»å¾å±è·åé®ç½©","mn":"ADBE Set Matte3-0001","ix":1,"v":{"a":0,"k":15,"ix":1}},{"ty":7,"nm":"ç¨äºé®ç½©","mn":"ADBE Set Matte3-0002","ix":2,"v":{"a":0,"k":4,"ix":2}},{"ty":7,"nm":"åè½¬é®ç½©","mn":"ADBE Set Matte3-0003","ix":3,"v":{"a":0,"k":0,"ix":3}},{"ty":7,"nm":"å¦æå¾å±å¤§å°ä¸å","mn":"ADBE Set Matte3-0004","ix":4,"v":{"a":0,"k":1,"ix":4}},{"ty":7,"nm":"å°é®ç½©ä¸åå§å¾ååæ","mn":"ADBE Set Matte3-0005","ix":5,"v":{"a":0,"k":1,"ix":5}},{"ty":7,"nm":"é¢ä¹é®ç½©å¾å±","mn":"ADBE Set Matte3-0006","ix":6,"v":{"a":0,"k":1,"ix":6}}]}],"shapes":[{"ty":"gr","it":[{"ind":0,"ty":"sh","ix":1,"ks":{"a":0,"k":{"i":[[-0.313,-4.318],[3.926,-0.284],[0.314,4.318],[-3.926,0.285]],"o":[[0.312,4.318],[-3.925,0.286],[-0.312,-4.318],[3.925,-0.285]],"v":[[7.108,-0.516],[0.567,7.817],[-7.108,0.515],[-0.567,-7.818]],"c":true},"ix":2},"nm":"è·¯å¾ 1","mn":"ADBE Vector Shape - Group","hd":false},{"ty":"fl","c":{"a":0,"k":[0.136999990426,0.097999999102,0.086000001197,1],"ix":4},"o":{"a":0,"k":100,"ix":5},"r":1,"bm":0,"nm":"å¡«å 1","mn":"ADBE Vector Graphic - Fill","hd":false},{"ty":"tr","p":{"a":0,"k":[7.67,8.354],"ix":2},"a":{"a":0,"k":[0,0],"ix":1},"s":{"a":0,"k":[100,100],"ix":3},"r":{"a":0,"k":0,"ix":6},"o":{"a":0,"k":100,"ix":7},"sk":{"a":0,"k":0,"ix":4},"sa":{"a":0,"k":0,"ix":5},"nm":"åæ¢"}],"nm":"ç» 1","np":2,"cix":2,"bm":0,"ix":1,"mn":"ADBE Vector Group","hd":false}],"ip":0,"op":150.000006109625,"st":0,"ct":1,"bm":0},{"ddd":0,"ind":9,"ty":4,"nm":"å¤´å","parent":13,"sr":1,"ks":{"o":{"a":0,"k":100,"ix":11},"r":{"a":1,"k":[{"i":{"x":[0.833],"y":[0.833]},"o":{"x":[0.167],"y":[0.167]},"t":11,"s":[5],"e":[-8]},{"i":{"x":[0.833],"y":[0.833]},"o":{"x":[0.167],"y":[0.167]},"t":21,"s":[-8],"e":[0]},{"t":27.0000010997325}],"ix":10,"x":"var $bm_rt;\nvar amp, freq, decay, n, n, t, t, v;\ntry {\n    amp = $bm_div(effect('Elastic: æè½¬')(1), 200);\n    freq = $bm_div(effect('Elastic: æè½¬')(2), 30);\n    decay = $bm_div(effect('Elastic: æè½¬')(3), 10);\n    $bm_rt = n = 0;\n    if (numKeys > 0) {\n        $bm_rt = n = nearestKey(time).index;\n        if (key(n).time > time) {\n            n--;\n        }\n    }\n    if (n == 0) {\n        $bm_rt = t = 0;\n    } else {\n        $bm_rt = t = $bm_sub(time, key(n).time);\n    }\n    if (n > 0) {\n        v = velocityAtTime($bm_sub(key(n).time, $bm_div(thisComp.frameDuration, 10)));\n        $bm_rt = $bm_sum(value, $bm_div($bm_mul($bm_mul(v, amp), Math.sin($bm_mul($bm_mul($bm_mul(freq, t), 2), Math.PI))), Math.exp($bm_mul(decay, t))));\n    } else {\n        $bm_rt = value;\n    }\n} catch (e$$4) {\n    $bm_rt = value = value;\n}"},"p":{"a":0,"k":[21.732,30.229,0],"ix":2,"l":2},"a":{"a":0,"k":[18.623,69.735,0],"ix":1,"l":2},"s":{"a":0,"k":[100,100,100],"ix":6,"l":2}},"ao":0,"ef":[{"ty":28,"nm":"è®¾ç½®é®ç½©","np":8,"mn":"ADBE Set Matte3","ix":1,"en":1,"ef":[{"ty":10,"nm":"ä»å¾å±è·åé®ç½©","mn":"ADBE Set Matte3-0001","ix":1,"v":{"a":0,"k":15,"ix":1}},{"ty":7,"nm":"ç¨äºé®ç½©","mn":"ADBE Set Matte3-0002","ix":2,"v":{"a":0,"k":4,"ix":2}},{"ty":7,"nm":"åè½¬é®ç½©","mn":"ADBE Set Matte3-0003","ix":3,"v":{"a":0,"k":0,"ix":3}},{"ty":7,"nm":"å¦æå¾å±å¤§å°ä¸å","mn":"ADBE Set Matte3-0004","ix":4,"v":{"a":0,"k":1,"ix":4}},{"ty":7,"nm":"å°é®ç½©ä¸åå§å¾ååæ","mn":"ADBE Set Matte3-0005","ix":5,"v":{"a":0,"k":1,"ix":5}},{"ty":7,"nm":"é¢ä¹é®ç½©å¾å±","mn":"ADBE Set Matte3-0006","ix":6,"v":{"a":0,"k":1,"ix":6}}]},{"ty":5,"nm":"Elastic: æè½¬","np":5,"mn":"Pseudo/MDS Elastic Controller","ix":4,"en":1,"ef":[{"ty":0,"nm":"Amplitude","mn":"Pseudo/MDS Elastic Controller-0001","ix":1,"v":{"a":0,"k":25,"ix":1}},{"ty":0,"nm":"Frequency","mn":"Pseudo/MDS Elastic Controller-0002","ix":2,"v":{"a":0,"k":45,"ix":2}},{"ty":0,"nm":"Decay","mn":"Pseudo/MDS Elastic Controller-0003","ix":3,"v":{"a":0,"k":60,"ix":3}}]},{"ty":5,"nm":"Elastic: Bend - CC Bend It","np":5,"mn":"Pseudo/MDS Elastic Controller","ix":5,"en":1,"ef":[{"ty":0,"nm":"Amplitude","mn":"Pseudo/MDS Elastic Controller-0001","ix":1,"v":{"a":0,"k":23,"ix":1}},{"ty":0,"nm":"Frequency","mn":"Pseudo/MDS Elastic Controller-0002","ix":2,"v":{"a":0,"k":40,"ix":2}},{"ty":0,"nm":"Decay","mn":"Pseudo/MDS Elastic Controller-0003","ix":3,"v":{"a":0,"k":60,"ix":3}}]},{"ty":34,"nm":"ææ§","np":6,"mn":"ADBE FreePin3","ix":6,"en":1,"ef":[{"ty":7,"nm":"äººå¶å¼æ","mn":"ADBE FreePin3 Puppet Engine","ix":1,"v":{"a":0,"k":2,"ix":1}},{"ty":0,"nm":"ç½æ ¼æè½¬è°æ´","mn":"ADBE FreePin3 Auto Rotate Pins","ix":2,"v":{"a":0,"k":20,"ix":2}},{"ty":7,"nm":"å¨éæèæ¯ä¸","mn":"ADBE FreePin3 On Transparent","ix":3,"v":{"a":0,"k":0,"ix":3}},{"ty":"","nm":"arap","np":3,"mn":"ADBE FreePin3 ARAP Group","ix":4,"en":1,"ef":[{"ty":6,"nm":"èªå¨è¿½è¸ªå½¢ç¶","mn":"ADBE FreePin3 Outlines","ix":1,"v":0},{"ty":"","nm":"ç½æ ¼","np":1,"mn":"ADBE FreePin3 Mesh Group","ix":2,"en":1,"ef":[]}]}]}],"shapes":[{"ty":"gr","it":[{"ind":0,"ty":"sh","ix":1,"ks":{"a":0,"k":{"i":[[-21.088,2.931],[-7.547,19.303],[5.822,0.983],[13.974,-17.265],[0.926,-1.566],[0.758,-1.991],[-2.709,-11.718],[-1.428,-2.309]],"o":[[33.744,-4.69],[-5.614,-2.329],[-21.282,-3.589],[-1.126,1.392],[-1.044,1.763],[-4.397,11.535],[0.368,1.591],[0.47,-12.21]],"v":[[-11.03,2.293],[45.725,-29.237],[28.224,-34.102],[-33.711,-18.214],[-30.638,-6.749],[-41.328,-5.995],[-40.384,29.743],[-37.438,37.69]],"c":true},"ix":2},"nm":"è·¯å¾ 1","mn":"ADBE Vector Shape - Group","hd":false},{"ty":"fl","c":{"a":0,"k":[0.2,0.2,0.2,1],"ix":4},"o":{"a":0,"k":100,"ix":5},"r":1,"bm":0,"nm":"å¡«å 1","mn":"ADBE Vector Graphic - Fill","hd":false},{"ty":"tr","p":{"a":0,"k":[51.349,40.824],"ix":2},"a":{"a":0,"k":[0,0],"ix":1},"s":{"a":0,"k":[100,100],"ix":3},"r":{"a":0,"k":0,"ix":6},"o":{"a":0,"k":100,"ix":7},"sk":{"a":0,"k":0,"ix":4},"sa":{"a":0,"k":0,"ix":5},"nm":"åæ¢"}],"nm":"ç» 1","np":2,"cix":2,"bm":0,"ix":1,"mn":"ADBE Vector Group","hd":false},{"ty":"gr","it":[{"ind":0,"ty":"sh","ix":1,"ks":{"a":0,"k":{"i":[[5.834,0],[12.807,-15.823],[-1.189,-3.877],[0.827,0],[0.56,-1.469],[-2.603,-11.26],[-2.244,-2.778],[-1.485,0],[-0.499,0.158],[-0.13,2.057],[-6.122,2.439],[-5.523,0],[-5.654,-1.007],[-6.086,-2.664],[-3.073,-1.159],[-4.82,0],[-2.314,1.095],[-2.125,7.776],[1.31,5.84],[24.096,4.065]],"o":[[-14.701,0],[-2.139,2.644],[-0.871,-0.089],[-4.585,0],[-5.097,13.372],[0.745,3.223],[0.966,1.197],[0.505,0],[1.964,-0.626],[0.716,-11.354],[4.086,-1.627],[4.281,0],[6.03,1.075],[3.008,1.317],[4.691,1.768],[2.782,0],[5.238,-2.479],[1.968,-7.202],[-3.755,-16.741],[-6.066,-1.023]],"v":[[0.202,-41.68],[-47.519,-22.535],[-47.584,-12.657],[-50.152,-12.814],[-56.921,-8.881],[-56.175,29.764],[-52.043,39.821],[-48.152,41.68],[-46.636,41.445],[-43.163,36.995],[-29.828,15.658],[-15.548,13.239],[-0.784,14.737],[17.625,21.232],[26.817,25.069],[40.939,28.424],[48.62,26.774],[59.716,11.319],[60.708,-8.335],[18.136,-40.138]],"c":true},"ix":2},"nm":"è·¯å¾ 1","mn":"ADBE Vector Shape - Group","hd":false},{"ind":1,"ty":"sh","ix":2,"ks":{"a":0,"k":{"i":[[-16.67,0],[-5.5,-0.928],[-3.968,-17.695],[1.535,-5.618],[4.716,-2.232],[1.912,0],[3.935,1.483],[9.731,1.735],[5.245,0],[5.072,-2.02],[0.677,-10.745],[0.523,2.262],[-4.397,11.534],[-1.085,0],[-1.899,0],[-0.259,0.437],[-1.126,1.392]],"o":[[5.81,0],[16.731,2.822],[1.274,5.679],[-1.335,4.884],[-1.764,0.835],[-4.11,0],[-9.212,-3.473],[-5.088,-0.907],[-5.565,0],[-9.852,3.926],[-1.663,-2.058],[-2.709,-11.718],[0.206,-0.541],[1.919,0],[0.982,0],[0.926,-1.565],[10.362,-12.804]],"v":[[0.202,-36.68],[17.305,-35.207],[55.829,-7.241],[54.893,10.001],[46.482,22.254],[40.939,23.424],[28.579,20.39],[0.094,9.815],[-15.548,8.239],[-31.678,11.013],[-48.153,36.68],[-51.304,28.637],[-52.248,-7.1],[-50.152,-7.814],[-43.54,-7.273],[-41.557,-7.855],[-43.632,-19.389]],"c":true},"ix":2},"nm":"è·¯å¾ 2","mn":"ADBE Vector Shape - Group","hd":false},{"ty":"mm","mm":1,"nm":"åå¹¶è·¯å¾ 1","mn":"ADBE Vector Filter - Merge","hd":false},{"ty":"fl","c":{"a":0,"k":[0.136999990426,0.097999999102,0.086000001197,1],"ix":4},"o":{"a":0,"k":100,"ix":5},"r":1,"bm":0,"nm":"å¡«å 1","mn":"ADBE Vector Graphic - Fill","hd":false},{"ty":"tr","p":{"a":0,"k":[62.268,41.93],"ix":2},"a":{"a":0,"k":[0,0],"ix":1},"s":{"a":0,"k":[100,100],"ix":3},"r":{"a":0,"k":0,"ix":6},"o":{"a":0,"k":100,"ix":7},"sk":{"a":0,"k":0,"ix":4},"sa":{"a":0,"k":0,"ix":5},"nm":"åæ¢"}],"nm":"ç» 2","np":4,"cix":2,"bm":0,"ix":2,"mn":"ADBE Vector Group","hd":false},{"ty":"gr","it":[{"ind":0,"ty":"sh","ix":1,"ks":{"a":0,"k":{"i":[[0.253,0],[0.483,0.598],[0.631,2.731],[-4.826,12.662],[-2.353,0],[-1.231,-0.141],[-0.716,-0.04],[0.259,0.84],[-1.415,1.749],[-14.157,0],[-5.93,-1],[-3.514,-15.669],[1.859,-6.804],[4.611,-2.182],[2.408,0],[4.468,1.683],[2.978,1.303],[6.322,1.127],[4.43,0],[4.386,-1.747],[0.565,-8.967],[0.982,-0.313]],"o":[[-0.742,0],[-1.946,-2.408],[-2.527,-10.929],[0.588,-1.541],[1.106,0],[0.833,0.096],[-0.233,-0.935],[-1.199,-3.884],[12.186,-15.057],[5.695,0],[23.011,3.882],[1.22,5.437],[-1.953,7.14],[-1.978,0.936],[-4.4,0],[-3.012,-1.135],[-6.221,-2.723],[-5.801,-1.034],[-5.846,0],[-9.511,3.79],[-0.065,1.029],[-0.25,0.079]],"v":[[-48.191,39.18],[-50.136,38.251],[-53.778,29.201],[-54.623,-7.991],[-50.191,-10.314],[-46.583,-10.026],[-44.179,-9.792],[-45.04,-12.763],[-45.614,-20.962],[0.162,-39.18],[17.683,-37.673],[58.23,-7.788],[57.266,10.66],[47.512,24.514],[40.9,25.925],[27.658,22.73],[18.59,18.943],[-0.383,12.277],[-15.587,10.74],[-30.792,13.336],[-45.696,36.837],[-47.433,39.062]],"c":true},"ix":2},"nm":"è·¯å¾ 1","mn":"ADBE Vector Shape - Group","hd":false},{"ty":"fl","c":{"a":0,"k":[0.136999990426,0.136999990426,0.136999990426,1],"ix":4},"o":{"a":0,"k":100,"ix":5},"r":1,"bm":0,"nm":"å¡«å 1","mn":"ADBE Vector Graphic - Fill","hd":false},{"ty":"tr","p":{"a":0,"k":[62.307,41.93],"ix":2},"a":{"a":0,"k":[0,0],"ix":1},"s":{"a":0,"k":[100,100],"ix":3},"r":{"a":0,"k":0,"ix":6},"o":{"a":0,"k":100,"ix":7},"sk":{"a":0,"k":0,"ix":4},"sa":{"a":0,"k":0,"ix":5},"nm":"åæ¢"}],"nm":"ç» 3","np":2,"cix":2,"bm":0,"ix":3,"mn":"ADBE Vector Group","hd":false}],"ip":0,"op":150.000006109625,"st":0,"ct":1,"bm":0},{"ddd":0,"ind":10,"ty":4,"nm":"å¤´åé´å½±","parent":9,"sr":1,"ks":{"o":{"a":0,"k":100,"ix":11},"r":{"a":0,"k":0,"ix":10},"p":{"a":0,"k":[64.711,60.532,0],"ix":2,"l":2},"a":{"a":0,"k":[46.838,17.293,0],"ix":1,"l":2},"s":{"a":0,"k":[100,100,100],"ix":6,"l":2}},"ao":0,"ef":[{"ty":28,"nm":"è®¾ç½®é®ç½©","np":8,"mn":"ADBE Set Matte3","ix":1,"en":1,"ef":[{"ty":10,"nm":"ä»å¾å±è·åé®ç½©","mn":"ADBE Set Matte3-0001","ix":1,"v":{"a":0,"k":15,"ix":1}},{"ty":7,"nm":"ç¨äºé®ç½©","mn":"ADBE Set Matte3-0002","ix":2,"v":{"a":0,"k":4,"ix":2}},{"ty":7,"nm":"åè½¬é®ç½©","mn":"ADBE Set Matte3-0003","ix":3,"v":{"a":0,"k":0,"ix":3}},{"ty":7,"nm":"å¦æå¾å±å¤§å°ä¸å","mn":"ADBE Set Matte3-0004","ix":4,"v":{"a":0,"k":1,"ix":4}},{"ty":7,"nm":"å°é®ç½©ä¸åå§å¾ååæ","mn":"ADBE Set Matte3-0005","ix":5,"v":{"a":0,"k":1,"ix":5}},{"ty":7,"nm":"é¢ä¹é®ç½©å¾å±","mn":"ADBE Set Matte3-0006","ix":6,"v":{"a":0,"k":1,"ix":6}}]}],"shapes":[{"ty":"gr","it":[{"ind":0,"ty":"sh","ix":1,"ks":{"a":0,"k":{"i":[[12.666,-0.5],[0,0],[-0.498,-13.126],[0,0],[-6.337,2.463],[-10.052,-2.304],[-8.769,-3.928],[-5.446,2.544],[-1.384,2.286],[0,0]],"o":[[0,0],[-12.666,0.501],[0,0],[3.493,-5.915],[9.632,-3.744],[9.327,2.138],[5.488,2.458],[2.366,-1.106],[0,0],[-0.499,-13.127]],"v":[[22.289,-16.79],[-23.726,-14.973],[-45.85,9.803],[-45.603,16.314],[-29.339,0.722],[-2.589,-0.778],[23.602,12.193],[40.807,14.746],[46.348,9.43],[46.225,6.167]],"c":true},"ix":2},"nm":"è·¯å¾ 1","mn":"ADBE Vector Shape - Group","hd":false},{"ty":"fl","c":{"a":0,"k":[0.925,0.681999954523,0.616000007181,1],"ix":4},"o":{"a":0,"k":100,"ix":5},"r":1,"bm":0,"nm":"å¡«å 1","mn":"ADBE Vector Graphic - Fill","hd":false},{"ty":"tr","p":{"a":0,"k":[46.598,17.54],"ix":2},"a":{"a":0,"k":[0,0],"ix":1},"s":{"a":0,"k":[100,100],"ix":3},"r":{"a":0,"k":0,"ix":6},"o":{"a":0,"k":100,"ix":7},"sk":{"a":0,"k":0,"ix":4},"sa":{"a":0,"k":0,"ix":5},"nm":"åæ¢"}],"nm":"ç» 1","np":2,"cix":2,"bm":0,"ix":1,"mn":"ADBE Vector Group","hd":false}],"ip":0,"op":150.000006109625,"st":0,"ct":1,"bm":7},{"ddd":0,"ind":11,"ty":4,"nm":"å´2","parent":12,"sr":1,"ks":{"o":{"a":0,"k":100,"ix":11},"r":{"a":0,"k":0,"ix":10},"p":{"a":0,"k":[24.357,17.636,0],"ix":2,"l":2},"a":{"a":0,"k":[-3.075,27.067,0],"ix":1,"l":2},"s":{"a":0,"k":[100,100,100],"ix":6,"l":2}},"ao":0,"ef":[{"ty":28,"nm":"è®¾ç½®é®ç½©","np":8,"mn":"ADBE Set Matte3","ix":1,"en":1,"ef":[{"ty":10,"nm":"ä»å¾å±è·åé®ç½©","mn":"ADBE Set Matte3-0001","ix":1,"v":{"a":0,"k":15,"ix":1}},{"ty":7,"nm":"ç¨äºé®ç½©","mn":"ADBE Set Matte3-0002","ix":2,"v":{"a":0,"k":4,"ix":2}},{"ty":7,"nm":"åè½¬é®ç½©","mn":"ADBE Set Matte3-0003","ix":3,"v":{"a":0,"k":0,"ix":3}},{"ty":7,"nm":"å¦æå¾å±å¤§å°ä¸å","mn":"ADBE Set Matte3-0004","ix":4,"v":{"a":0,"k":1,"ix":4}},{"ty":7,"nm":"å°é®ç½©ä¸åå§å¾ååæ","mn":"ADBE Set Matte3-0005","ix":5,"v":{"a":0,"k":1,"ix":5}},{"ty":7,"nm":"é¢ä¹é®ç½©å¾å±","mn":"ADBE Set Matte3-0006","ix":6,"v":{"a":0,"k":1,"ix":6}}]}],"shapes":[{"ty":"gr","it":[{"ind":0,"ty":"sh","ix":1,"ks":{"a":0,"k":{"i":[[3.905,0],[4.732,3.114],[-0.963,1.465],[-1.465,-0.964],[-0.265,0.103],[-0.637,-1.622],[1.616,-0.65]],"o":[[-3.521,0],[-1.464,-0.963],[0.963,-1.465],[7.12,4.684],[1.624,-0.624],[0.637,1.622],[-0.203,0.082]],"v":[[-0.319,31.954],[-13.123,28.006],[-14.03,23.609],[-9.634,22.703],[4.079,24.946],[8.182,26.745],[6.426,30.845]],"c":true},"ix":2},"nm":"è·¯å¾ 1","mn":"ADBE Vector Shape - Group","hd":false},{"ty":"fl","c":{"a":0,"k":[0.137254908681,0.098039217293,0.086274512112,1],"ix":4},"o":{"a":0,"k":100,"ix":5},"r":1,"bm":0,"nm":"å¡«å 1","mn":"ADBE Vector Graphic - Fill","hd":false},{"ty":"tr","p":{"a":0,"k":[0,0],"ix":2},"a":{"a":0,"k":[0,0],"ix":1},"s":{"a":0,"k":[100,100],"ix":3},"r":{"a":0,"k":0,"ix":6},"o":{"a":0,"k":100,"ix":7},"sk":{"a":0,"k":0,"ix":4},"sa":{"a":0,"k":0,"ix":5},"nm":"åæ¢"}],"nm":"ç» 1","np":2,"cix":2,"bm":0,"ix":1,"mn":"ADBE Vector Group","hd":false}],"ip":0,"op":150.000006109625,"st":0,"ct":1,"bm":0},{"ddd":0,"ind":12,"ty":3,"nm":"å´","parent":2,"sr":1,"ks":{"o":{"a":0,"k":100,"ix":11},"r":{"a":0,"k":0,"ix":10},"p":{"a":0,"k":[-6.018,53.076,0],"ix":2,"l":2},"a":{"a":0,"k":[24.179,17.584,0],"ix":1,"l":2},"s":{"a":0,"k":[196.078,196.078,100],"ix":6,"l":2}},"ao":0,"ip":0,"op":150.000006109625,"st":0,"ct":1,"bm":0},{"ddd":0,"ind":13,"ty":4,"nm":"å¤´é¨","parent":14,"sr":1,"ks":{"o":{"a":0,"k":100,"ix":11},"r":{"a":1,"k":[{"i":{"x":[0.667],"y":[1]},"o":{"x":[0.333],"y":[0]},"t":40,"s":[0],"e":[-10]},{"i":{"x":[0.667],"y":[1]},"o":{"x":[0.333],"y":[0]},"t":48,"s":[-10],"e":[0]},{"t":56.0000022809268}],"ix":10},"p":{"a":0,"k":[72.367,11.188,0],"ix":2,"l":2},"a":{"a":0,"k":[69.257,91.429,0],"ix":1,"l":2},"s":{"a":1,"k":[{"i":{"x":[0.833,0.833,0.833],"y":[0.833,0.833,0.833]},"o":{"x":[0.167,0.167,0.167],"y":[0.167,0.167,0.167]},"t":15,"s":[80,110,100],"e":[100,100,100]},{"t":25.0000010182709}],"ix":6,"l":2}},"ao":0,"ef":[{"ty":28,"nm":"è®¾ç½®é®ç½©","np":8,"mn":"ADBE Set Matte3","ix":1,"en":1,"ef":[{"ty":10,"nm":"ä»å¾å±è·åé®ç½©","mn":"ADBE Set Matte3-0001","ix":1,"v":{"a":0,"k":15,"ix":1}},{"ty":7,"nm":"ç¨äºé®ç½©","mn":"ADBE Set Matte3-0002","ix":2,"v":{"a":0,"k":4,"ix":2}},{"ty":7,"nm":"åè½¬é®ç½©","mn":"ADBE Set Matte3-0003","ix":3,"v":{"a":0,"k":0,"ix":3}},{"ty":7,"nm":"å¦æå¾å±å¤§å°ä¸å","mn":"ADBE Set Matte3-0004","ix":4,"v":{"a":0,"k":1,"ix":4}},{"ty":7,"nm":"å°é®ç½©ä¸åå§å¾ååæ","mn":"ADBE Set Matte3-0005","ix":5,"v":{"a":0,"k":1,"ix":5}},{"ty":7,"nm":"é¢ä¹é®ç½©å¾å±","mn":"ADBE Set Matte3-0006","ix":6,"v":{"a":0,"k":1,"ix":6}}]}],"shapes":[{"ty":"gr","it":[{"ind":0,"ty":"sh","ix":1,"ks":{"a":0,"k":{"i":[[21.98,-1.634],[0,0],[1.623,22.919],[0,0],[-22.188,1.896],[0,0],[1.264,23.013],[0,0]],"o":[[0,0],[-21.981,1.634],[0,0],[1.406,23.193],[0,0],[21.748,-1.389],[0,0],[1.622,22.919]],"v":[[7.113,19.946],[-1.616,20.555],[-46.95,-20.601],[-46.512,-14.669],[-1.315,25.384],[6.767,24.618],[45.686,-20.995],[45.083,-27.281]],"c":true},"ix":2},"nm":"è·¯å¾ 1","mn":"ADBE Vector Shape - Group","hd":false},{"ty":"fl","c":{"a":0,"k":[0.925,0.681999954523,0.616000007181,1],"ix":4},"o":{"a":0,"k":100,"ix":5},"r":1,"bm":0,"nm":"å¡«å 1","mn":"ADBE Vector Graphic - Fill","hd":false},{"ty":"tr","p":{"a":0,"k":[69.608,70.723],"ix":2},"a":{"a":0,"k":[0,0],"ix":1},"s":{"a":0,"k":[100,100],"ix":3},"r":{"a":0,"k":0,"ix":6},"o":{"a":0,"k":100,"ix":7},"sk":{"a":0,"k":0,"ix":4},"sa":{"a":0,"k":0,"ix":5},"nm":"åæ¢"}],"nm":"ç» 1","np":2,"cix":2,"bm":0,"ix":1,"mn":"ADBE Vector Group","hd":false},{"ty":"gr","it":[{"ind":0,"ty":"sh","ix":1,"ks":{"a":0,"k":{"i":[[14.708,0],[0,0],[0.678,-0.051],[0,0],[-1.124,-15.876],[0,0],[-25.118,0],[-1.156,0.086],[0,0],[1.924,27.178],[0,0]],"o":[[0,0],[-0.678,0],[0,0],[-15.493,1.152],[0,0],[1.821,25.73],[1.155,0],[0,0],[26.466,-1.967],[0,0],[-1.065,-15.035]],"v":[[21.966,-50.429],[21.964,-50.429],[19.921,-50.352],[-26.292,-46.917],[-52.35,-16.037],[-50.893,4.546],[-2.853,50.429],[0.632,50.299],[7.042,49.823],[51.551,-3.033],[50.094,-23.617]],"c":true},"ix":2},"nm":"è·¯å¾ 1","mn":"ADBE Vector Shape - Group","hd":false},{"ind":1,"ty":"sh","ix":2,"ks":{"a":0,"k":{"i":[[-0.554,0],[-0.886,-12.525],[0,0],[23.666,-1.76],[0,0],[1.03,0],[1.65,23.3],[0,0],[-12.721,0.945],[0,0]],"o":[[12.014,-0.001],[0,0],[1.725,24.375],[0,0],[-1.043,0.077],[-22.349,0],[0,0],[-0.927,-13.102],[0,0],[0.561,-0.041]],"v":[[21.964,-45.429],[45.105,-23.264],[46.562,-2.68],[6.671,44.837],[0.26,45.314],[-2.853,45.429],[-45.906,4.194],[-47.363,-16.39],[-25.921,-41.93],[20.29,-45.367]],"c":true},"ix":2},"nm":"è·¯å¾ 2","mn":"ADBE Vector Shape - Group","hd":false},{"ty":"mm","mm":1,"nm":"åå¹¶è·¯å¾ 1","mn":"ADBE Vector Filter - Merge","hd":false},{"ty":"fl","c":{"a":0,"k":[0.136999990426,0.097999999102,0.086000001197,1],"ix":4},"o":{"a":0,"k":100,"ix":5},"r":1,"bm":0,"nm":"å¡«å 1","mn":"ADBE Vector Graphic - Fill","hd":false},{"ty":"tr","p":{"a":0,"k":[68.69,50.679],"ix":2},"a":{"a":0,"k":[0,0],"ix":1},"s":{"a":0,"k":[100,100],"ix":3},"r":{"a":0,"k":0,"ix":6},"o":{"a":0,"k":100,"ix":7},"sk":{"a":0,"k":0,"ix":4},"sa":{"a":0,"k":0,"ix":5},"nm":"åæ¢"}],"nm":"ç» 2","np":4,"cix":2,"bm":0,"ix":2,"mn":"ADBE Vector Group","hd":false},{"ty":"gr","it":[{"ind":0,"ty":"sh","ix":1,"ks":{"a":0,"k":{"i":[[1.093,0],[1.729,24.426],[0,0],[-14.123,1.05],[0,0],[-0.616,0],[-0.972,-13.732],[0,0],[25.095,-1.866],[0,0]],"o":[[-23.812,0],[0,0],[-1.027,-14.506],[0,0],[0.617,-0.046],[13.403,0],[0,0],[1.826,25.807],[0,0],[-1.094,0.081]],"v":[[-2.851,47.928],[-48.399,4.37],[-49.856,-16.214],[-26.105,-44.424],[20.106,-47.859],[21.964,-47.928],[47.6,-23.44],[49.057,-2.857],[6.857,47.329],[0.446,47.807]],"c":true},"ix":2},"nm":"è·¯å¾ 1","mn":"ADBE Vector Shape - Group","hd":false},{"ty":"fl","c":{"a":0,"k":[0.972999961703,0.808000033509,0.764999988032,1],"ix":4},"o":{"a":0,"k":100,"ix":5},"r":1,"bm":0,"nm":"å¡«å 1","mn":"ADBE Vector Graphic - Fill","hd":false},{"ty":"tr","p":{"a":0,"k":[68.69,50.679],"ix":2},"a":{"a":0,"k":[0,0],"ix":1},"s":{"a":0,"k":[100,100],"ix":3},"r":{"a":0,"k":0,"ix":6},"o":{"a":0,"k":100,"ix":7},"sk":{"a":0,"k":0,"ix":4},"sa":{"a":0,"k":0,"ix":5},"nm":"åæ¢"}],"nm":"ç» 3","np":2,"cix":2,"bm":0,"ix":3,"mn":"ADBE Vector Group","hd":false},{"ty":"gr","it":[{"ind":0,"ty":"sh","ix":1,"ks":{"a":0,"k":{"i":[[0,0],[-5.058,-3.142]],"o":[[0,0],[0,0]],"v":[[0.76,-3.654],[2.529,3.654]],"c":false},"ix":2},"nm":"è·¯å¾ 1","mn":"ADBE Vector Shape - Group","hd":false},{"ty":"st","c":{"a":0,"k":[0.136999990426,0.097999999102,0.086000001197,1],"ix":3},"o":{"a":0,"k":100,"ix":4},"w":{"a":0,"k":4,"ix":5},"lc":2,"lj":2,"bm":0,"nm":"æè¾¹ 1","mn":"ADBE Vector Graphic - Stroke","hd":false},{"ty":"tr","p":{"a":0,"k":[12.529,49.312],"ix":2},"a":{"a":0,"k":[0,0],"ix":1},"s":{"a":0,"k":[100,100],"ix":3},"r":{"a":0,"k":0,"ix":6},"o":{"a":0,"k":100,"ix":7},"sk":{"a":0,"k":0,"ix":4},"sa":{"a":0,"k":0,"ix":5},"nm":"åæ¢"}],"nm":"ç» 4","np":2,"cix":2,"bm":0,"ix":4,"mn":"ADBE Vector Group","hd":false},{"ty":"gr","it":[{"ind":0,"ty":"sh","ix":1,"ks":{"a":0,"k":{"i":[[2.185,5.386],[-4.342,1.795],[0.988,-0.401],[-2.825,-6.961],[-4.369,1.773],[-0.011,0.005]],"o":[[-2.817,-6.943],[-1.087,-0.174],[-4.37,1.773],[2.824,6.961],[0.011,-0.004],[-3.716,-0.595]],"v":[[-1.943,2.24],[0.822,-13.557],[-2.319,-13.25],[-5.116,2.564],[7.909,11.958],[7.941,11.942]],"c":true},"ix":2},"nm":"è·¯å¾ 1","mn":"ADBE Vector Shape - Group","hd":false},{"ty":"fl","c":{"a":0,"k":[0.972999961703,0.827000038297,0.804000016755,1],"ix":4},"o":{"a":0,"k":100,"ix":5},"r":1,"bm":0,"nm":"å¡«å 1","mn":"ADBE Vector Graphic - Fill","hd":false},{"ty":"tr","p":{"a":0,"k":[13.03,50.134],"ix":2},"a":{"a":0,"k":[0,0],"ix":1},"s":{"a":0,"k":[100,100],"ix":3},"r":{"a":0,"k":0,"ix":6},"o":{"a":0,"k":100,"ix":7},"sk":{"a":0,"k":0,"ix":4},"sa":{"a":0,"k":0,"ix":5},"nm":"åæ¢"}],"nm":"ç» 5","np":2,"cix":2,"bm":0,"ix":5,"mn":"ADBE Vector Group","hd":false},{"ty":"gr","it":[{"ind":0,"ty":"sh","ix":1,"ks":{"a":0,"k":{"i":[[6.161,0],[1.263,-0.512],[0.827,-4.674],[-1.715,-4.226],[-6.161,0],[-1.263,0.511],[-0.827,4.674],[1.715,4.227]],"o":[[-1.389,0],[-3.711,1.506],[-0.69,3.901],[3.135,7.728],[1.389,0],[3.711,-1.506],[0.69,-3.901],[-3.136,-7.727]],"v":[[-2.998,-18.01],[-6.994,-17.238],[-14.134,-7.514],[-12.544,5.09],[2.998,18.01],[6.994,17.238],[14.134,7.514],[12.544,-5.09]],"c":true},"ix":2},"nm":"è·¯å¾ 1","mn":"ADBE Vector Shape - Group","hd":false},{"ind":1,"ty":"sh","ix":2,"ks":{"a":0,"k":{"i":[[-0.729,0],[-2.388,-5.883],[4.369,-1.773],[0.729,0],[2.388,5.884],[-4.369,1.773]],"o":[[3.985,0],[2.824,6.961],[-0.676,0.274],[-3.985,0],[-2.824,-6.961],[0.676,-0.274]],"v":[[-2.998,-13.01],[7.911,-3.21],[5.114,12.604],[2.998,13.01],[-7.911,3.21],[-5.114,-12.604]],"c":true},"ix":2},"nm":"è·¯å¾ 2","mn":"ADBE Vector Shape - Group","hd":false},{"ty":"mm","mm":1,"nm":"åå¹¶è·¯å¾ 1","mn":"ADBE Vector Filter - Merge","hd":false},{"ty":"fl","c":{"a":0,"k":[0.136999990426,0.097999999102,0.086000001197,1],"ix":4},"o":{"a":0,"k":100,"ix":5},"r":1,"bm":0,"nm":"å¡«å 1","mn":"ADBE Vector Graphic - Fill","hd":false},{"ty":"tr","p":{"a":0,"k":[15.825,49.488],"ix":2},"a":{"a":0,"k":[0,0],"ix":1},"s":{"a":0,"k":[100,100],"ix":3},"r":{"a":0,"k":0,"ix":6},"o":{"a":0,"k":100,"ix":7},"sk":{"a":0,"k":0,"ix":4},"sa":{"a":0,"k":0,"ix":5},"nm":"åæ¢"}],"nm":"ç» 6","np":4,"cix":2,"bm":0,"ix":6,"mn":"ADBE Vector Group","hd":false},{"ty":"gr","it":[{"ind":0,"ty":"sh","ix":1,"ks":{"a":0,"k":{"i":[[0,0],[2.757,6.794],[-5.735,2.327],[-1.065,0],[-2.756,-6.794],[0.609,-3.444],[2.939,-1.192],[1.065,0]],"o":[[-5.153,0],[-3.394,-8.368],[0.963,-0.391],[5.154,0],[1.541,3.797],[-0.683,3.865],[-0.963,0.391],[0,0]],"v":[[3.668,15.509],[-9.557,4.151],[-5.384,-14.92],[-2.328,-15.509],[10.897,-4.15],[12.342,7.078],[6.724,14.92],[3.668,15.509]],"c":true},"ix":2},"nm":"è·¯å¾ 1","mn":"ADBE Vector Shape - Group","hd":false},{"ty":"fl","c":{"a":0,"k":[0.925,0.681999954523,0.616000007181,1],"ix":4},"o":{"a":0,"k":100,"ix":5},"r":1,"bm":0,"nm":"å¡«å 1","mn":"ADBE Vector Graphic - Fill","hd":false},{"ty":"tr","p":{"a":0,"k":[15.154,49.488],"ix":2},"a":{"a":0,"k":[0,0],"ix":1},"s":{"a":0,"k":[100,100],"ix":3},"r":{"a":0,"k":0,"ix":6},"o":{"a":0,"k":100,"ix":7},"sk":{"a":0,"k":0,"ix":4},"sa":{"a":0,"k":0,"ix":5},"nm":"åæ¢"}],"nm":"ç» 7","np":2,"cix":2,"bm":0,"ix":7,"mn":"ADBE Vector Group","hd":false},{"ty":"gr","it":[{"ind":0,"ty":"sh","ix":1,"ks":{"a":0,"k":{"i":[[0,0],[3.995,-4.417]],"o":[[0,0],[0,0]],"v":[[-2.155,-3.756],[-1.84,3.756]],"c":false},"ix":2},"nm":"è·¯å¾ 1","mn":"ADBE Vector Shape - Group","hd":false},{"ty":"st","c":{"a":0,"k":[0.136999990426,0.097999999102,0.086000001197,1],"ix":3},"o":{"a":0,"k":100,"ix":4},"w":{"a":0,"k":4,"ix":5},"lc":2,"lj":2,"bm":0,"nm":"æè¾¹ 1","mn":"ADBE Vector Graphic - Stroke","hd":false},{"ty":"tr","p":{"a":0,"k":[124.694,40.29],"ix":2},"a":{"a":0,"k":[0,0],"ix":1},"s":{"a":0,"k":[100,100],"ix":3},"r":{"a":0,"k":0,"ix":6},"o":{"a":0,"k":100,"ix":7},"sk":{"a":0,"k":0,"ix":4},"sa":{"a":0,"k":0,"ix":5},"nm":"åæ¢"}],"nm":"ç» 8","np":2,"cix":2,"bm":0,"ix":8,"mn":"ADBE Vector Group","hd":false},{"ty":"gr","it":[{"ind":0,"ty":"sh","ix":1,"ks":{"a":0,"k":{"i":[[-1.385,5.645],[4.556,1.15],[-1.037,-0.254],[1.79,-7.296],[4.579,1.124],[0.012,0.003]],"o":[[1.786,-7.277],[1.051,-0.329],[4.579,1.124],[-1.792,7.295],[-0.011,-0.003],[3.591,-1.124]],"v":[[1.701,1.737],[-3.315,-13.496],[-0.161,-13.645],[4.889,1.6],[-6.645,12.775],[-6.679,12.763]],"c":true},"ix":2},"nm":"è·¯å¾ 1","mn":"ADBE Vector Shape - Group","hd":false},{"ty":"fl","c":{"a":0,"k":[0.972999961703,0.827000038297,0.804000016755,1],"ix":4},"o":{"a":0,"k":100,"ix":5},"r":1,"bm":0,"nm":"å¡«å 1","mn":"ADBE Vector Graphic - Fill","hd":false},{"ty":"tr","p":{"a":0,"k":[124.61,42.099],"ix":2},"a":{"a":0,"k":[0,0],"ix":1},"s":{"a":0,"k":[100,100],"ix":3},"r":{"a":0,"k":0,"ix":6},"o":{"a":0,"k":100,"ix":7},"sk":{"a":0,"k":0,"ix":4},"sa":{"a":0,"k":0,"ix":5},"nm":"åæ¢"}],"nm":"ç» 9","np":2,"cix":2,"bm":0,"ix":9,"mn":"ADBE Vector Group","hd":false},{"ty":"gr","it":[{"ind":0,"ty":"sh","ix":1,"ks":{"a":0,"k":{"i":[[0.845,0],[0,0],[2.187,-8.914],[-1.245,-3.76],[-3.889,-0.954],[-0.845,0],[-2.188,8.915],[1.246,3.761],[3.889,0.954]],"o":[[0,0],[-6.69,0],[-1.087,4.43],[1.492,4.505],[0.816,0.2],[6.69,0],[1.087,-4.43],[-1.492,-4.505],[-0.815,-0.2]],"v":[[1.932,-18.368],[1.932,-18.368],[-13.147,-3.226],[-12.901,9.475],[-4.434,18.066],[-1.931,18.368],[13.147,3.227],[12.901,-9.475],[4.434,-18.066]],"c":true},"ix":2},"nm":"è·¯å¾ 1","mn":"ADBE Vector Shape - Group","hd":false},{"ind":1,"ty":"sh","ix":2,"ks":{"a":0,"k":{"i":[[-4.215,0],[-0.434,-0.107],[1.79,-7.296],[4.214,0],[0.433,0.106],[-1.79,7.295]],"o":[[0.439,0],[4.579,1.123],[-1.621,6.606],[-0.441,0],[-4.579,-1.124],[1.621,-6.606]],"v":[[1.932,-13.368],[3.242,-13.209],[8.292,2.035],[-1.931,13.368],[-3.241,13.21],[-8.292,-2.035]],"c":true},"ix":2},"nm":"è·¯å¾ 2","mn":"ADBE Vector Shape - Group","hd":false},{"ty":"mm","mm":1,"nm":"åå¹¶è·¯å¾ 1","mn":"ADBE Vector Filter - Merge","hd":false},{"ty":"fl","c":{"a":0,"k":[0.136999990426,0.097999999102,0.086000001197,1],"ix":4},"o":{"a":0,"k":100,"ix":5},"r":1,"bm":0,"nm":"å¡«å 1","mn":"ADBE Vector Graphic - Fill","hd":false},{"ty":"tr","p":{"a":0,"k":[121.207,41.663],"ix":2},"a":{"a":0,"k":[0,0],"ix":1},"s":{"a":0,"k":[100,100],"ix":3},"r":{"a":0,"k":0,"ix":6},"o":{"a":0,"k":100,"ix":7},"sk":{"a":0,"k":0,"ix":4},"sa":{"a":0,"k":0,"ix":5},"nm":"åæ¢"}],"nm":"ç» 10","np":4,"cix":2,"bm":0,"ix":10,"mn":"ADBE Vector Group","hd":false},{"ty":"gr","it":[{"ind":0,"ty":"sh","ix":1,"ks":{"a":0,"k":{"i":[[5.447,0],[0.621,0.152],[-2.151,8.769],[-5.448,0],[-0.622,-0.153],[2.152,-8.769]],"o":[[-0.644,0],[-6.011,-1.476],[1.882,-7.67],[0.644,0],[6.01,1.475],[-1.882,7.671]],"v":[[-1.931,15.868],[-3.837,15.638],[-10.719,-2.631],[1.931,-15.868],[3.838,-15.638],[10.719,2.63]],"c":true},"ix":2},"nm":"è·¯å¾ 1","mn":"ADBE Vector Shape - Group","hd":false},{"ty":"fl","c":{"a":0,"k":[0.925,0.681999954523,0.616000007181,1],"ix":4},"o":{"a":0,"k":100,"ix":5},"r":1,"bm":0,"nm":"å¡«å 1","mn":"ADBE Vector Graphic - Fill","hd":false},{"ty":"tr","p":{"a":0,"k":[121.207,41.664],"ix":2},"a":{"a":0,"k":[0,0],"ix":1},"s":{"a":0,"k":[100,100],"ix":3},"r":{"a":0,"k":0,"ix":6},"o":{"a":0,"k":100,"ix":7},"sk":{"a":0,"k":0,"ix":4},"sa":{"a":0,"k":0,"ix":5},"nm":"åæ¢"}],"nm":"ç» 11","np":2,"cix":2,"bm":0,"ix":11,"mn":"ADBE Vector Group","hd":false}],"ip":0,"op":150.000006109625,"st":0,"ct":1,"bm":0},{"ddd":0,"ind":14,"ty":4,"nm":"èº«ä½","parent":3,"sr":1,"ks":{"o":{"a":0,"k":100,"ix":11},"r":{"a":0,"k":0,"ix":10},"p":{"a":0,"k":[-0.727,5.424,0],"ix":2,"l":2},"a":{"a":0,"k":[74.548,62.54,0],"ix":1,"l":2},"s":{"a":0,"k":[100,100,100],"ix":6,"l":2}},"ao":0,"ef":[{"ty":28,"nm":"è®¾ç½®é®ç½©","np":8,"mn":"ADBE Set Matte3","ix":1,"en":1,"ef":[{"ty":10,"nm":"ä»å¾å±è·åé®ç½©","mn":"ADBE Set Matte3-0001","ix":1,"v":{"a":0,"k":15,"ix":1}},{"ty":7,"nm":"ç¨äºé®ç½©","mn":"ADBE Set Matte3-0002","ix":2,"v":{"a":0,"k":4,"ix":2}},{"ty":7,"nm":"åè½¬é®ç½©","mn":"ADBE Set Matte3-0003","ix":3,"v":{"a":0,"k":0,"ix":3}},{"ty":7,"nm":"å¦æå¾å±å¤§å°ä¸å","mn":"ADBE Set Matte3-0004","ix":4,"v":{"a":0,"k":1,"ix":4}},{"ty":7,"nm":"å°é®ç½©ä¸åå§å¾ååæ","mn":"ADBE Set Matte3-0005","ix":5,"v":{"a":0,"k":1,"ix":5}},{"ty":7,"nm":"é¢ä¹é®ç½©å¾å±","mn":"ADBE Set Matte3-0006","ix":6,"v":{"a":0,"k":1,"ix":6}}]}],"shapes":[{"ty":"gr","it":[{"ind":0,"ty":"sh","ix":1,"ks":{"a":0,"k":{"i":[[0,0],[1.283,-4.208]],"o":[[0,0],[0,0]],"v":[[3.139,-4.501],[-3.139,4.501]],"c":false},"ix":2},"nm":"è·¯å¾ 1","mn":"ADBE Vector Shape - Group","hd":false},{"ty":"st","c":{"a":0,"k":[0.136999990426,0.097999999102,0.086000001197,1],"ix":3},"o":{"a":0,"k":100,"ix":4},"w":{"a":0,"k":4,"ix":5},"lc":2,"lj":2,"bm":0,"nm":"æè¾¹ 1","mn":"ADBE Vector Graphic - Stroke","hd":false},{"ty":"tr","p":{"a":0,"k":[34.955,51.56],"ix":2},"a":{"a":0,"k":[0,0],"ix":1},"s":{"a":0,"k":[100,100],"ix":3},"r":{"a":0,"k":0,"ix":6},"o":{"a":0,"k":100,"ix":7},"sk":{"a":0,"k":0,"ix":4},"sa":{"a":0,"k":0,"ix":5},"nm":"åæ¢"}],"nm":"ç» 1","np":2,"cix":2,"bm":0,"ix":1,"mn":"ADBE Vector Group","hd":false},{"ty":"gr","it":[{"ind":0,"ty":"sh","ix":1,"ks":{"a":0,"k":{"i":[[0,0],[1.218,-4.228]],"o":[[0,0],[0,0]],"v":[[3.069,-4.55],[-3.069,4.55]],"c":false},"ix":2},"nm":"è·¯å¾ 1","mn":"ADBE Vector Shape - Group","hd":false},{"ty":"st","c":{"a":0,"k":[0.136999990426,0.097999999102,0.086000001197,1],"ix":3},"o":{"a":0,"k":100,"ix":4},"w":{"a":0,"k":4,"ix":5},"lc":2,"lj":2,"bm":0,"nm":"æè¾¹ 1","mn":"ADBE Vector Graphic - Stroke","hd":false},{"ty":"tr","p":{"a":0,"k":[25.638,48.3],"ix":2},"a":{"a":0,"k":[0,0],"ix":1},"s":{"a":0,"k":[100,100],"ix":3},"r":{"a":0,"k":0,"ix":6},"o":{"a":0,"k":100,"ix":7},"sk":{"a":0,"k":0,"ix":4},"sa":{"a":0,"k":0,"ix":5},"nm":"åæ¢"}],"nm":"ç» 2","np":2,"cix":2,"bm":0,"ix":2,"mn":"ADBE Vector Group","hd":false},{"ty":"gr","it":[{"ind":0,"ty":"sh","ix":1,"ks":{"a":0,"k":{"i":[[6.186,3.948],[2.918,-4.969],[6.527,3.833],[0,0],[0.144,0.091],[-1.559,-0.915],[0,0],[-3.832,6.527]],"o":[[3.323,4.319],[-3.832,6.527],[0,0],[-0.148,-0.087],[1.043,1.354],[0,0],[6.527,3.833],[3.746,-6.379]],"v":[[7.814,-13.644],[8.807,1.737],[-10.029,6.636],[-15.604,3.362],[-16.031,3.082],[-12.126,6.537],[-6.551,9.811],[12.285,4.912]],"c":true},"ix":2},"nm":"è·¯å¾ 1","mn":"ADBE Vector Shape - Group","hd":false},{"ty":"fl","c":{"a":0,"k":[0.925,0.681999954523,0.616000007181,1],"ix":4},"o":{"a":0,"k":100,"ix":5},"r":1,"bm":0,"nm":"å¡«å 1","mn":"ADBE Vector Graphic - Fill","hd":false},{"ty":"tr","p":{"a":0,"k":[26.639,60.308],"ix":2},"a":{"a":0,"k":[0,0],"ix":1},"s":{"a":0,"k":[100,100],"ix":3},"r":{"a":0,"k":0,"ix":6},"o":{"a":0,"k":100,"ix":7},"sk":{"a":0,"k":0,"ix":4},"sa":{"a":0,"k":0,"ix":5},"nm":"åæ¢"}],"nm":"ç» 3","np":2,"cix":2,"bm":0,"ix":3,"mn":"ADBE Vector Group","hd":false},{"ty":"gr","it":[{"ind":0,"ty":"sh","ix":1,"ks":{"a":0,"k":{"i":[[0.451,-0.562],[1.208,0.108],[0.188,-0.08],[0.007,-0.232],[-0.011,-0.699],[-0.217,-1.192],[-0.334,-1.167],[-0.238,1.068],[-0.138,0.528],[-0.282,0.121],[-1.117,-0.027],[-0.814,1.012],[0.785,0.956],[1.219,0.394]],"o":[[-0.814,1.012],[-1.118,-0.027],[-0.28,0.12],[-0.023,0.7],[0.021,1.209],[0.217,1.197],[0.767,-1.999],[0.21,-0.902],[0.078,-0.297],[0.188,-0.08],[1.209,0.107],[0.708,-0.88],[-0.715,-0.871],[0.091,0.849]],"v":[[0.379,-4.456],[-2.57,-2.841],[-4.465,-3.747],[-4.689,-2.434],[-4.654,-0.343],[-4.361,3.273],[-3.387,6.788],[-2.145,3.077],[-1.467,0.176],[-0.987,-0.572],[0.909,0.333],[3.857,-1.281],[3.96,-4.906],[0.939,-6.788]],"c":true},"ix":2},"nm":"è·¯å¾ 1","mn":"ADBE Vector Shape - Group","hd":false},{"ty":"fl","c":{"a":0,"k":[0.925,0.681999954523,0.616000007181,1],"ix":4},"o":{"a":0,"k":100,"ix":5},"r":1,"bm":0,"nm":"å¡«å 1","mn":"ADBE Vector Graphic - Fill","hd":false},{"ty":"tr","p":{"a":0,"k":[22.585,34.904],"ix":2},"a":{"a":0,"k":[0,0],"ix":1},"s":{"a":0,"k":[100,100],"ix":3},"r":{"a":0,"k":0,"ix":6},"o":{"a":0,"k":100,"ix":7},"sk":{"a":0,"k":0,"ix":4},"sa":{"a":0,"k":0,"ix":5},"nm":"åæ¢"}],"nm":"ç» 4","np":2,"cix":2,"bm":0,"ix":4,"mn":"ADBE Vector Group","hd":false},{"ty":"gr","it":[{"ind":0,"ty":"sh","ix":1,"ks":{"a":0,"k":{"i":[[4.323,0],[1.182,-0.332],[0.877,-9.135],[0.055,-1.771],[-0.004,-0.317],[-0.001,-0.104],[-8.651,-5.08],[0,0],[-3.324,0],[-3.351,5.706],[1.264,4.861],[4.309,2.53],[0,0],[0.558,0.295],[-0.326,0.405],[2.504,3.049]],"o":[[-1.391,0],[-6.424,1.804],[-0.18,1.874],[-0.011,0.326],[0.002,0.089],[-4.599,8.796],[0,0],[2.866,1.682],[6.653,0],[2.53,-4.309],[-1.264,-4.861],[0,0],[-0.547,-0.321],[0.348,-0.335],[2.001,-2.488],[-2.181,-2.657]],"v":[[-3.335,-27.211],[-7.212,-26.71],[-18.215,-10.224],[-18.508,-4.749],[-18.512,-3.8],[-18.508,-3.499],[-11.376,21.364],[-5.801,24.639],[3.661,27.211],[19.88,17.96],[21.842,3.741],[13.201,-7.72],[7.625,-10.994],[5.971,-11.925],[6.982,-13.035],[7.052,-22.967]],"c":true},"ix":2},"nm":"è·¯å¾ 1","mn":"ADBE Vector Shape - Group","hd":false},{"ind":1,"ty":"sh","ix":2,"ks":{"a":0,"k":{"i":[[-0.918,0],[-1.371,-1.669],[0.707,-0.88],[1.093,0],[0.081,0.007],[0.21,0],[0.007,-0.003],[0.078,-0.297],[0.132,-0.476],[0.399,-0.922],[-1.02,0],[-2.29,-1.344],[0,0],[3.833,-6.528],[4.731,0],[2.175,1.276],[0,0],[-3.833,6.527],[-0.027,0.839],[-0.166,1.729],[-5.479,1.54]],"o":[[2.417,0],[0.785,0.956],[-0.759,0.943],[-0.079,0],[-1.073,-0.026],[-0.009,0],[-0.283,0.121],[-0.184,0.703],[-0.09,0.325],[1.403,-0.431],[1.883,0],[0,0],[6.528,3.832],[-2.555,4.352],[-2.364,0],[0,0],[-6.527,-3.833],[0.338,-0.793],[0.054,-1.735],[0.48,-5.006],[0.733,-0.206]],"v":[[-3.335,-22.211],[3.189,-19.794],[3.086,-16.169],[0.378,-14.544],[0.138,-14.555],[-1.732,-15.466],[-1.758,-15.461],[-2.238,-14.713],[-3.076,-11.156],[-4.158,-8.1],[-0.611,-8.74],[5.094,-6.683],[10.669,-3.408],[15.568,15.428],[3.661,22.211],[-3.268,20.327],[-8.844,17.053],[-13.743,-1.784],[-13.512,-4.547],[-13.237,-9.746],[-5.861,-21.897]],"c":true},"ix":2},"nm":"è·¯å¾ 2","mn":"ADBE Vector Shape - Group","hd":false},{"ty":"mm","mm":1,"nm":"åå¹¶è·¯å¾ 1","mn":"ADBE Vector Filter - Merge","hd":false},{"ty":"fl","c":{"a":0,"k":[0.136999990426,0.097999999102,0.086000001197,1],"ix":4},"o":{"a":0,"k":100,"ix":5},"r":1,"bm":0,"nm":"å¡«å 1","mn":"ADBE Vector Graphic - Fill","hd":false},{"ty":"tr","p":{"a":0,"k":[23.356,49.792],"ix":2},"a":{"a":0,"k":[0,0],"ix":1},"s":{"a":0,"k":[100,100],"ix":3},"r":{"a":0,"k":0,"ix":6},"o":{"a":0,"k":100,"ix":7},"sk":{"a":0,"k":0,"ix":4},"sa":{"a":0,"k":0,"ix":5},"nm":"åæ¢"}],"nm":"ç» 5","np":4,"cix":2,"bm":0,"ix":5,"mn":"ADBE Vector Group","hd":false},{"ty":"gr","it":[{"ind":0,"ty":"sh","ix":1,"ks":{"a":0,"k":{"i":[[5.771,0],[2.483,1.457],[0,0],[1.095,4.215],[-2.083,3.681],[0.004,0.309],[-0.008,0.245],[-0.171,1.795],[-8.032,2.257],[-1.146,0],[-1.711,-2.086],[1.35,-1.68],[2.598,0],[0.129,0.01],[0.092,0.01],[0.059,-0.251],[-2.202,-1.293],[0,0],[-1.096,-4.215],[2.192,-3.732]],"o":[[-2.879,0],[0,0],[-3.733,-2.191],[-1.074,-4.127],[0.032,-0.21],[-0.004,-0.276],[0.055,-1.775],[0.287,-2.985],[0.949,-0.265],[3.582,0],[1.622,1.974],[-0.51,0.633],[-0.127,0],[-0.096,-0.003],[-0.069,0.3],[2.602,0.034],[0,0],[3.732,2.19],[1.096,4.214],[-2.904,4.946]],"v":[[2.738,24.711],[-5.458,22.483],[-11.034,19.208],[-18.521,9.273],[-16.956,-2.82],[-16.935,-3.837],[-16.934,-4.625],[-16.65,-9.984],[-7.461,-24.304],[-4.258,-24.711],[4.197,-21.38],[4.111,-14.602],[-0.547,-12.044],[-0.931,-12.059],[-1.212,-12.079],[-1.406,-11.239],[5.436,-8.839],[11.012,-5.563],[18.5,4.37],[16.801,16.693]],"c":true},"ix":2},"nm":"è·¯å¾ 1","mn":"ADBE Vector Shape - Group","hd":false},{"ty":"fl","c":{"a":0,"k":[0.972999961703,0.808000033509,0.764999988032,1],"ix":4},"o":{"a":0,"k":100,"ix":5},"r":1,"bm":0,"nm":"å¡«å 1","mn":"ADBE Vector Graphic - Fill","hd":false},{"ty":"tr","p":{"a":0,"k":[24.28,49.792],"ix":2},"a":{"a":0,"k":[0,0],"ix":1},"s":{"a":0,"k":[100,100],"ix":3},"r":{"a":0,"k":0,"ix":6},"o":{"a":0,"k":100,"ix":7},"sk":{"a":0,"k":0,"ix":4},"sa":{"a":0,"k":0,"ix":5},"nm":"åæ¢"}],"nm":"ç» 6","np":2,"cix":2,"bm":0,"ix":6,"mn":"ADBE Vector Group","hd":false},{"ty":"gr","it":[{"ind":0,"ty":"sh","ix":1,"ks":{"a":0,"k":{"i":[[0.484,0],[0,0],[2.363,-2.108],[0.271,-3.469],[0.121,-0.858],[-1.998,-2.489],[-2.467,-0.193],[-1.042,0],[-2.025,4.874],[2.102,3.618],[2.878,0.359]],"o":[[0,0],[-3.073,0],[-2.529,2.254],[-0.077,0.978],[-0.361,2.564],[1.274,1.588],[0.963,0.076],[5.664,0],[2.003,-4.819],[-1.495,-2.573],[-0.476,-0.06]],"v":[[1.739,-12.831],[1.739,-12.831],[-6.692,-9.562],[-11.036,-0.685],[-11.36,2.039],[-10.132,9.998],[-4.494,12.682],[-1.46,12.831],[10.127,5.485],[9.967,-8.194],[3.186,-12.741]],"c":true},"ix":2},"nm":"è·¯å¾ 1","mn":"ADBE Vector Shape - Group","hd":false},{"ind":1,"ty":"sh","ix":2,"ks":{"a":0,"k":{"i":[[-3.593,0],[-0.273,-0.034],[2.068,-4.978],[2.87,0],[0.887,0.07],[-0.398,5.079]],"o":[[0.277,0],[4.129,0.515],[-1.479,3.56],[-0.866,0],[-3.825,-0.299],[0.369,-4.714]],"v":[[1.739,-7.831],[2.566,-7.78],[5.51,3.566],[-1.46,7.831],[-4.102,7.697],[-6.051,-0.295]],"c":true},"ix":2},"nm":"è·¯å¾ 2","mn":"ADBE Vector Shape - Group","hd":false},{"ty":"mm","mm":1,"nm":"åå¹¶è·¯å¾ 1","mn":"ADBE Vector Filter - Merge","hd":false},{"ty":"fl","c":{"a":0,"k":[0.136999990426,0.097999999102,0.086000001197,1],"ix":4},"o":{"a":0,"k":100,"ix":5},"r":1,"bm":0,"nm":"å¡«å 1","mn":"ADBE Vector Graphic - Fill","hd":false},{"ty":"tr","p":{"a":0,"k":[29.357,41.223],"ix":2},"a":{"a":0,"k":[0,0],"ix":1},"s":{"a":0,"k":[100,100],"ix":3},"r":{"a":0,"k":0,"ix":6},"o":{"a":0,"k":100,"ix":7},"sk":{"a":0,"k":0,"ix":4},"sa":{"a":0,"k":0,"ix":5},"nm":"åæ¢"}],"nm":"ç» 7","np":4,"cix":2,"bm":0,"ix":7,"mn":"ADBE Vector Group","hd":false},{"ty":"gr","it":[{"ind":0,"ty":"sh","ix":1,"ks":{"a":0,"k":{"i":[[1.698,0],[0.952,0.076],[1.243,1.549],[-0.333,2.359],[-0.083,1.055],[-4.676,0],[-0.373,-0.047],[-1.094,-1.881],[1.684,-4.051]],"o":[[-0.954,0],[-0.653,-0.05],[-1.321,-1.646],[0.12,-0.855],[0.482,-6.16],[0.381,0],[2.085,0.26],[1.692,2.914],[-2.412,5.806]],"v":[[-1.459,10.331],[-4.298,10.189],[-8.182,8.433],[-8.883,2.389],[-8.543,-0.49],[1.739,-10.331],[2.875,-10.261],[7.805,-6.94],[7.819,4.525]],"c":true},"ix":2},"nm":"è·¯å¾ 1","mn":"ADBE Vector Shape - Group","hd":false},{"ty":"fl","c":{"a":0,"k":[0.925,0.681999954523,0.616000007181,1],"ix":4},"o":{"a":0,"k":100,"ix":5},"r":1,"bm":0,"nm":"å¡«å 1","mn":"ADBE Vector Graphic - Fill","hd":false},{"ty":"tr","p":{"a":0,"k":[29.356,41.223],"ix":2},"a":{"a":0,"k":[0,0],"ix":1},"s":{"a":0,"k":[100,100],"ix":3},"r":{"a":0,"k":0,"ix":6},"o":{"a":0,"k":100,"ix":7},"sk":{"a":0,"k":0,"ix":4},"sa":{"a":0,"k":0,"ix":5},"nm":"åæ¢"}],"nm":"ç» 8","np":2,"cix":2,"bm":0,"ix":8,"mn":"ADBE Vector Group","hd":false},{"ty":"gr","it":[{"ind":0,"ty":"sh","ix":1,"ks":{"a":0,"k":{"i":[[-2.371,0],[0,0],[-1.209,-1.44],[3.281,0],[0,0],[0,-3.515],[0,-0.029]],"o":[[0,0],[2.028,0],[-0.345,-3.189],[0,0],[-3.515,0],[0,0.028],[1.161,-1.878]],"v":[[-29.259,0.083],[29.832,0.083],[34.861,2.459],[28.564,-3.224],[-28.497,-3.224],[-34.861,3.141],[-34.853,3.224]],"c":true},"ix":2},"nm":"è·¯å¾ 1","mn":"ADBE Vector Shape - Group","hd":false},{"ty":"fl","c":{"a":0,"k":[0.238999998803,0.238999998803,0.238999998803,1],"ix":4},"o":{"a":0,"k":100,"ix":5},"r":1,"bm":0,"nm":"å¡«å 1","mn":"ADBE Vector Graphic - Fill","hd":false},{"ty":"tr","p":{"a":0,"k":[73.894,31.775],"ix":2},"a":{"a":0,"k":[0,0],"ix":1},"s":{"a":0,"k":[100,100],"ix":3},"r":{"a":0,"k":0,"ix":6},"o":{"a":0,"k":100,"ix":7},"sk":{"a":0,"k":0,"ix":4},"sa":{"a":0,"k":0,"ix":5},"nm":"åæ¢"}],"nm":"ç» 9","np":2,"cix":2,"bm":0,"ix":9,"mn":"ADBE Vector Group","hd":false},{"ty":"gr","it":[{"ind":0,"ty":"sh","ix":1,"ks":{"a":0,"k":{"i":[[6.267,0],[0,0],[0,-6.266],[-6.266,0],[0,0],[0,6.266]],"o":[[0,0],[-6.266,0],[0,6.266],[0,0],[6.267,0],[0,-6.266]],"v":[[28.531,-11.364],[-28.531,-11.364],[-39.895,0],[-28.531,11.364],[28.531,11.364],[39.895,0]],"c":true},"ix":2},"nm":"è·¯å¾ 1","mn":"ADBE Vector Shape - Group","hd":false},{"ind":1,"ty":"sh","ix":2,"ks":{"a":0,"k":{"i":[[0,0],[0,-3.514],[3.515,0],[0,0],[0,3.515],[-3.514,0]],"o":[[3.515,0],[0,3.515],[0,0],[-3.514,0],[0,-3.514],[0,0]],"v":[[28.531,-6.364],[34.895,0],[28.531,6.364],[-28.531,6.364],[-34.895,0],[-28.531,-6.364]],"c":true},"ix":2},"nm":"è·¯å¾ 2","mn":"ADBE Vector Shape - Group","hd":false},{"ty":"mm","mm":1,"nm":"åå¹¶è·¯å¾ 1","mn":"ADBE Vector Filter - Merge","hd":false},{"ty":"fl","c":{"a":0,"k":[0.136999990426,0.097999999102,0.086000001197,1],"ix":4},"o":{"a":0,"k":100,"ix":5},"r":1,"bm":0,"nm":"å¡«å 1","mn":"ADBE Vector Graphic - Fill","hd":false},{"ty":"tr","p":{"a":0,"k":[73.928,34.916],"ix":2},"a":{"a":0,"k":[0,0],"ix":1},"s":{"a":0,"k":[100,100],"ix":3},"r":{"a":0,"k":0,"ix":6},"o":{"a":0,"k":100,"ix":7},"sk":{"a":0,"k":0,"ix":4},"sa":{"a":0,"k":0,"ix":5},"nm":"åæ¢"}],"nm":"ç» 10","np":4,"cix":2,"bm":0,"ix":10,"mn":"ADBE Vector Group","hd":false},{"ty":"gr","it":[{"ind":0,"ty":"sh","ix":1,"ks":{"a":0,"k":{"i":[[0,0],[0,4.887],[-4.888,0],[0,0],[0,-4.888],[4.887,0]],"o":[[-4.888,0],[0,-4.888],[0,0],[4.887,0],[0,4.887],[0,0]],"v":[[-28.531,8.864],[-37.395,0.001],[-28.531,-8.864],[28.531,-8.864],[37.395,0.001],[28.531,8.864]],"c":true},"ix":2},"nm":"è·¯å¾ 1","mn":"ADBE Vector Shape - Group","hd":false},{"ty":"fl","c":{"a":0,"k":[0.2,0.2,0.2,1],"ix":4},"o":{"a":0,"k":100,"ix":5},"r":1,"bm":0,"nm":"å¡«å 1","mn":"ADBE Vector Graphic - Fill","hd":false},{"ty":"tr","p":{"a":0,"k":[73.928,34.915],"ix":2},"a":{"a":0,"k":[0,0],"ix":1},"s":{"a":0,"k":[100,100],"ix":3},"r":{"a":0,"k":0,"ix":6},"o":{"a":0,"k":100,"ix":7},"sk":{"a":0,"k":0,"ix":4},"sa":{"a":0,"k":0,"ix":5},"nm":"åæ¢"}],"nm":"ç» 11","np":2,"cix":2,"bm":0,"ix":11,"mn":"ADBE Vector Group","hd":false},{"ty":"gr","it":[{"ind":0,"ty":"sh","ix":1,"ks":{"a":0,"k":{"i":[[0,0],[-8.815,0],[-6.183,2.406],[0,0],[0,0]],"o":[[6.183,2.406],[8.816,0],[0,0],[0,0],[0,0]],"v":[[-23.051,7.023],[0,10.889],[23.051,7.023],[23.051,-10.889],[-23.051,-10.889]],"c":true},"ix":2},"nm":"è·¯å¾ 1","mn":"ADBE Vector Shape - Group","hd":false},{"ty":"fl","c":{"a":0,"k":[0.925,0.681999954523,0.616000007181,1],"ix":4},"o":{"a":0,"k":100,"ix":5},"r":1,"bm":0,"nm":"å¡«å 1","mn":"ADBE Vector Graphic - Fill","hd":false},{"ty":"tr","p":{"a":0,"k":[73.929,13.39],"ix":2},"a":{"a":0,"k":[0,0],"ix":1},"s":{"a":0,"k":[100,100],"ix":3},"r":{"a":0,"k":0,"ix":6},"o":{"a":0,"k":100,"ix":7},"sk":{"a":0,"k":0,"ix":4},"sa":{"a":0,"k":0,"ix":5},"nm":"åæ¢"}],"nm":"ç» 12","np":2,"cix":2,"bm":0,"ix":12,"mn":"ADBE Vector Group","hd":false},{"ty":"gr","it":[{"ind":0,"ty":"sh","ix":1,"ks":{"a":0,"k":{"i":[[2.762,0],[0,0],[0,-2.762],[0,0],[-2.761,0],[0,0],[0,2.762],[0,0]],"o":[[0,0],[-2.761,0],[0,0],[0,2.762],[0,0],[2.762,0],[0,0],[0,-2.762]],"v":[[23.051,-21.829],[-23.051,-21.829],[-28.051,-16.829],[-28.051,16.829],[-23.051,21.829],[23.051,21.829],[28.051,16.829],[28.051,-16.829]],"c":true},"ix":2},"nm":"è·¯å¾ 1","mn":"ADBE Vector Shape - Group","hd":false},{"ind":1,"ty":"sh","ix":2,"ks":{"a":0,"k":{"i":[[0,0],[0,0],[0,0],[0,0]],"o":[[0,0],[0,0],[0,0],[0,0]],"v":[[23.051,16.829],[-23.051,16.829],[-23.051,-16.829],[23.051,-16.829]],"c":true},"ix":2},"nm":"è·¯å¾ 2","mn":"ADBE Vector Shape - Group","hd":false},{"ty":"mm","mm":1,"nm":"åå¹¶è·¯å¾ 1","mn":"ADBE Vector Filter - Merge","hd":false},{"ty":"fl","c":{"a":0,"k":[0.136999990426,0.097999999102,0.086000001197,1],"ix":4},"o":{"a":0,"k":100,"ix":5},"r":1,"bm":0,"nm":"å¡«å 1","mn":"ADBE Vector Graphic - Fill","hd":false},{"ty":"tr","p":{"a":0,"k":[73.928,22.079],"ix":2},"a":{"a":0,"k":[0,0],"ix":1},"s":{"a":0,"k":[100,100],"ix":3},"r":{"a":0,"k":0,"ix":6},"o":{"a":0,"k":100,"ix":7},"sk":{"a":0,"k":0,"ix":4},"sa":{"a":0,"k":0,"ix":5},"nm":"åæ¢"}],"nm":"ç» 13","np":4,"cix":2,"bm":0,"ix":13,"mn":"ADBE Vector Group","hd":false},{"ty":"gr","it":[{"ind":0,"ty":"sh","ix":1,"ks":{"a":0,"k":{"i":[[0,0],[0,1.381],[0,0],[-1.381,0],[0,0],[0,-1.381],[0,0],[1.381,0]],"o":[[-1.381,0],[0,0],[0,-1.381],[0,0],[1.381,0],[0,0],[0,1.381],[0,0]],"v":[[-23.051,19.329],[-25.551,16.829],[-25.551,-16.829],[-23.051,-19.329],[23.051,-19.329],[25.551,-16.829],[25.551,16.829],[23.051,19.329]],"c":true},"ix":2},"nm":"è·¯å¾ 1","mn":"ADBE Vector Shape - Group","hd":false},{"ty":"fl","c":{"a":0,"k":[0.972999961703,0.808000033509,0.764999988032,1],"ix":4},"o":{"a":0,"k":100,"ix":5},"r":1,"bm":0,"nm":"å¡«å 1","mn":"ADBE Vector Graphic - Fill","hd":false},{"ty":"tr","p":{"a":0,"k":[73.929,22.079],"ix":2},"a":{"a":0,"k":[0,0],"ix":1},"s":{"a":0,"k":[100,100],"ix":3},"r":{"a":0,"k":0,"ix":6},"o":{"a":0,"k":100,"ix":7},"sk":{"a":0,"k":0,"ix":4},"sa":{"a":0,"k":0,"ix":5},"nm":"åæ¢"}],"nm":"ç» 14","np":2,"cix":2,"bm":0,"ix":14,"mn":"ADBE Vector Group","hd":false},{"ty":"gr","it":[{"ind":0,"ty":"sh","ix":1,"ks":{"a":0,"k":{"i":[[-15.835,0],[0,0],[-3.922,-15.467],[18.675,0],[0,0],[2.153,-17.293]],"o":[[0,0],[16.687,0],[-1.054,-18.411],[0,0],[-17.877,0],[4.681,-14.269]],"v":[[-32.319,-12.529],[31.661,-12.529],[66.243,16.513],[31.294,-16.513],[-31.492,-16.513],[-66.243,14.171]],"c":true},"ix":2},"nm":"è·¯å¾ 1","mn":"ADBE Vector Shape - Group","hd":false},{"ty":"fl","c":{"a":0,"k":[0.224000010771,0.226999993418,0.226999993418,1],"ix":4},"o":{"a":0,"k":100,"ix":5},"r":1,"bm":0,"nm":"å¡«å 1","mn":"ADBE Vector Graphic - Fill","hd":false},{"ty":"tr","p":{"a":0,"k":[75.027,55.792],"ix":2},"a":{"a":0,"k":[0,0],"ix":1},"s":{"a":0,"k":[100,100],"ix":3},"r":{"a":0,"k":0,"ix":6},"o":{"a":0,"k":100,"ix":7},"sk":{"a":0,"k":0,"ix":4},"sa":{"a":0,"k":0,"ix":5},"nm":"åæ¢"}],"nm":"ç» 15","np":2,"cix":2,"bm":0,"ix":15,"mn":"ADBE Vector Group","hd":false},{"ty":"gr","it":[{"ind":0,"ty":"sh","ix":1,"ks":{"a":0,"k":{"i":[[22.084,0],[0,0],[0,-22.084],[-2.761,0],[0,0],[-0.938,0.937],[0,1.326]],"o":[[0,0],[-22.084,0],[0,2.762],[0,0],[1.326,0],[0.937,-0.938],[0,-22.084]],"v":[[31.394,-22.526],[-31.394,-22.526],[-71.445,17.526],[-66.445,22.526],[66.445,22.526],[69.981,21.061],[71.445,17.526]],"c":true},"ix":2},"nm":"è·¯å¾ 1","mn":"ADBE Vector Shape - Group","hd":false},{"ind":1,"ty":"sh","ix":2,"ks":{"a":0,"k":{"i":[[0,0],[0,-19.359],[0,0],[-19.358,0]],"o":[[19.358,0],[0,0],[0,-19.359],[0,0]],"v":[[31.394,-17.526],[66.445,17.526],[-66.445,17.526],[-31.394,-17.526]],"c":true},"ix":2},"nm":"è·¯å¾ 2","mn":"ADBE Vector Shape - Group","hd":false},{"ty":"mm","mm":1,"nm":"åå¹¶è·¯å¾ 1","mn":"ADBE Vector Filter - Merge","hd":false},{"ty":"fl","c":{"a":0,"k":[0.136999990426,0.097999999102,0.086000001197,1],"ix":4},"o":{"a":0,"k":100,"ix":5},"r":1,"bm":0,"nm":"å¡«å 1","mn":"ADBE Vector Graphic - Fill","hd":false},{"ty":"tr","p":{"a":0,"k":[74.928,56.804],"ix":2},"a":{"a":0,"k":[0,0],"ix":1},"s":{"a":0,"k":[100,100],"ix":3},"r":{"a":0,"k":0,"ix":6},"o":{"a":0,"k":100,"ix":7},"sk":{"a":0,"k":0,"ix":4},"sa":{"a":0,"k":0,"ix":5},"nm":"åæ¢"}],"nm":"ç» 16","np":4,"cix":2,"bm":0,"ix":16,"mn":"ADBE Vector Group","hd":false},{"ty":"gr","it":[{"ind":0,"ty":"sh","ix":1,"ks":{"a":0,"k":{"i":[[0,0],[0,1.381],[-20.706,0],[0,0],[0,-20.706],[1.381,0]],"o":[[-1.381,0],[0,-20.706],[0,0],[20.706,0],[0,1.381],[0,0]],"v":[[-66.445,20.025],[-68.945,17.525],[-31.394,-20.025],[31.394,-20.025],[68.945,17.525],[66.445,20.025]],"c":true},"ix":2},"nm":"è·¯å¾ 1","mn":"ADBE Vector Shape - Group","hd":false},{"ty":"fl","c":{"a":0,"k":[0.176000004189,0.176000004189,0.176000004189,1],"ix":4},"o":{"a":0,"k":100,"ix":5},"r":1,"bm":0,"nm":"å¡«å 1","mn":"ADBE Vector Graphic - Fill","hd":false},{"ty":"tr","p":{"a":0,"k":[74.928,56.804],"ix":2},"a":{"a":0,"k":[0,0],"ix":1},"s":{"a":0,"k":[100,100],"ix":3},"r":{"a":0,"k":0,"ix":6},"o":{"a":0,"k":100,"ix":7},"sk":{"a":0,"k":0,"ix":4},"sa":{"a":0,"k":0,"ix":5},"nm":"åæ¢"}],"nm":"ç» 17","np":2,"cix":2,"bm":0,"ix":17,"mn":"ADBE Vector Group","hd":false}],"ip":0,"op":150.000006109625,"st":0,"ct":1,"bm":0},{"ddd":0,"ind":15,"ty":4,"nm":"ååº","parent":1,"sr":1,"ks":{"o":{"a":0,"k":100,"ix":11},"r":{"a":0,"k":0,"ix":10},"p":{"a":0,"k":[66.842,-87.232,0],"ix":2,"l":2},"a":{"a":0,"k":[100.438,100.438,0],"ix":1,"l":2},"s":{"a":1,"k":[{"i":{"x":[0.338,0.338,0.667],"y":[1,1,1]},"o":{"x":[0.637,0.637,0.333],"y":[-0.004,-0.004,0]},"t":0,"s":[0,0,100],"e":[100,100,100]},{"t":15.0000006109625}],"ix":6,"l":2}},"ao":0,"shapes":[{"ty":"gr","it":[{"ind":0,"ty":"sh","ix":1,"ks":{"a":0,"k":{"i":[[55.333,0],[0,0],[0,55.332],[-55.333,0],[0,-55.333]],"o":[[0,0],[-55.333,0],[0,-55.333],[55.333,0],[0,55.332]],"v":[[0,100.188],[0,100.188],[-100.188,0],[0,-100.188],[100.188,0]],"c":true},"ix":2},"nm":"è·¯å¾ 1","mn":"ADBE Vector Shape - Group","hd":false},{"ty":"fl","c":{"a":0,"k":[1,1,1,1],"ix":4},"o":{"a":0,"k":100,"ix":5},"r":1,"bm":0,"nm":"å¡«å 1","mn":"ADBE Vector Graphic - Fill","hd":false},{"ty":"tr","p":{"a":0,"k":[100.438,100.438],"ix":2},"a":{"a":0,"k":[0,0],"ix":1},"s":{"a":0,"k":[100,100],"ix":3},"r":{"a":0,"k":0,"ix":6},"o":{"a":0,"k":100,"ix":7},"sk":{"a":0,"k":0,"ix":4},"sa":{"a":0,"k":0,"ix":5},"nm":"åæ¢"}],"nm":"ç» 1","np":2,"cix":2,"bm":0,"ix":1,"mn":"ADBE Vector Group","hd":false}],"ip":0,"op":150.000006109625,"st":0,"ct":1,"bm":0}],"markers":[]}